data_memory.sv
module data_memory # (
    parameter DATA_WIDTH    = 32,
              BYTE_WIDTH    = 8, 
              START_ADDRESS = 32'h10000,
              END_ADDRESS   = 32'h1FFFF
)(
    input  logic                        clk_i, we_i, byte_op_i,
    input  logic [DATA_WIDTH-1:0]       addr_i,
    input  logic [DATA_WIDTH-1:0]       wd_i,
    output logic [DATA_WIDTH-1:0]       rd_o
);

logic [BYTE_WIDTH-1:0]  data_ram [END_ADDRESS:0];
logic [DATA_WIDTH-1:0]  addr;

assign addr = byte_op_i ? addr_i : (addr_i & 32'hFFFFFFFC);

initial begin
    // $readmemh("gaussian.mem", data_ram, START_ADDRESS);
    $readmemh("triangle.mem", data_ram, START_ADDRESS);
    // $readmemh("sine.mem", data_ram, START_ADDRESS);
    // $readmemh("noisy.mem", data_ram, START_ADDRESS);
    for (int i = 0; i < START_ADDRESS; i++) begin
        data_ram[i] = {BYTE_WIDTH{1'b0}};
    end
end

always_comb begin
    case (byte_op_i)
        1'b0: rd_o = {data_ram[addr+3], data_ram[addr+2], data_ram[addr+1], data_ram[addr+0]};
        1'b1: rd_o = {{3*BYTE_WIDTH{1'b0}}, data_ram[addr]};    // only implementing LBU
        default: rd_o = {DATA_WIDTH{1'b0}};
    endcase
end

always_ff @(negedge clk_i) begin
    if (we_i)
        case (byte_op_i)
            1'b1: data_ram[addr] <= wd_i[BYTE_WIDTH-1:0];
            1'b0: begin
                data_ram[addr+0] <= wd_i[BYTE_WIDTH-1:0];
                data_ram[addr+1] <= wd_i[2*BYTE_WIDTH-1:BYTE_WIDTH];
                data_ram[addr+2] <= wd_i[3*BYTE_WIDTH-1:2*BYTE_WIDTH];
                data_ram[addr+3] <= wd_i[4*BYTE_WIDTH-1:3*BYTE_WIDTH];
            end
        endcase
end

endmodule

cacheline.sv

module cacheline #(
    parameter   width = 32,
			 	tag_bits = 30
               // BYTE_WIDTH = 8
)(
	input logic clk_i, write_enable_i, cache_enable_i, byte_op_i,
	input logic [width-1:0] address_i , write_data_i,
	//output signals
	output logic [width-1:0] read_data_o,
	//memory interface signals
	input logic [width-1:0] mem_incoming_data_i,
	output logic [width-1:0] mem_address_o , mem_write_data_o,
	output logic mem_write_enable_o , mem_byte_op_o
);
//--------------------------data_structure---------------------------

	logic [width-1:0] cache_data[3:0];
	logic [tag_bits-1:0] cache_tag [3:0];
	logic valid [3:0];
    logic [1:0] counter;
//------------------------internal_signals----------------------------
    logic [tag_bits-1 :0] tag;
    logic [1:0] byteoffset;
    logic hit;
    logic [1:0] wayhit;

//-------------------------assign_values--------------------------------
    assign tag = address_i[31:2];
    assign mem_byte_op_o = 1'b0;
    assign byteoffset = address_i[1:0];
    assign mem_address_o = address_i;
    assign mem_write_enable_o = write_enable_i;
//----------------------------------------------------------------------
    initial begin
        hit = 1'b0;
        for(int i = 0 ; i<4 ; i++) begin
            valid[i[1:0]] = 1'b0;
            cache_data[i[1:0]] = 32'b0;
            cache_tag [i[1:0]] = 30'b0;
        end
    end

    always_comb begin
        if(cache_enable_i) begin
            //check for tag match 
            for(int i = 0 ; i < 4 ; i++) begin
                if(cache_tag[i[1:0]] == tag) begin
                    hit = valid[i[1:0]];
                    wayhit = i[1:0];
                    break;
                end
                else
                    hit = 1'b0;
            end
            //load word
            if(!write_enable_i) begin
                mem_byte_op_o = 0;
                //mem_write_enable_o <= 1'b0;
                if(hit) begin
                    if(byte_op_i)begin
                        case(byteoffset)
                        2'b00 : read_data_o = { {24'b0},mem_incoming_data_i[7:0]};
                        2'b01 : read_data_o = { {24'b0},mem_incoming_data_i[15:8]};
                        2'b10 : read_data_o = { {24'b0},mem_incoming_data_i[23:16]};
                        2'b11 : read_data_o = { {24'b0},mem_incoming_data_i[31:24]};
                        endcase
                    end
                    else begin
                        read_data_o = cache_data[wayhit];    
                    end
                end
                else begin
                    if(byte_op_i)begin
                        case(byteoffset)
                        2'b00 : read_data_o = { {24'b0},mem_incoming_data_i[7:0]};
                        2'b01 : read_data_o = { {24'b0},mem_incoming_data_i[15:8]};
                        2'b10 : read_data_o = { {24'b0},mem_incoming_data_i[23:16]};
                        2'b11 : read_data_o = { {24'b0},mem_incoming_data_i[31:24]};
                        endcase
                    end
                    else begin
                    //mem_address_o <= address_i;
                        read_data_o = mem_incoming_data_i;
                    end
                end
            end
            //store word
            else begin
                mem_byte_op_o = byte_op_i;
                //mem_address_o <= address_i;
                //mem_write_enable_o <= 1'b1;
                if(hit) begin

                    mem_write_data_o = write_data_i;
                end
                else begin
                    // cache_tag[counter] = tag;
                    // cache_data[counter] = write_data_i;
                    // valid[counter] = 1'b1;
                    mem_write_data_o = write_data_i;
                end
            end
        end
    end

    always_ff@(negedge clk_i)begin
        if (cache_enable_i==1'b1)begin

            
            if((write_enable_i==1'b1) || (hit==1'b0)) begin
                counter <= counter + 1'b1;
            end
            if((write_enable_i == 1'b0) && (hit==1'b0))begin //load word and not in cache
                $display("neil");
                cache_data[counter] <= mem_incoming_data_i;
                cache_tag[counter] <= tag;
                //cache_data[counter] <= mem_incoming_data_i;
                valid[counter] <= 1'b1;
            end
            else if((write_enable_i==1'b1) &&(hit==1'b1)) begin
                if(byte_op_i) begin
                    case(byteoffset)
                        2'b00 : cache_data[wayhit][7:0] <= write_data_i[7:0];
                        2'b01 : cache_data[wayhit][15:8] <= write_data_i[7:0];
                        2'b10 : cache_data[wayhit][23:16] <= write_data_i[7:0];
                        2'b11 : cache_data[wayhit][31:24] <= write_data_i[7:0];
                    endcase
                end
                else begin
                    
                    cache_data[wayhit] <= write_data_i;
                end
                //cache_tag[wayhit] <= tag;
                //cache_data[wayhit] <= write_data_i;
                valid[wayhit] <= 1'b1;
            end
            else if((write_enable_i==1'b1)&& (hit==1'b0))begin
                if(byte_op_i) begin
                    case(byteoffset)
                        2'b00 : cache_data[counter][7:0] <= write_data_i[7:0];
                        2'b01 : cache_data[counter][15:8] <= write_data_i[7:0];
                        2'b10 : cache_data[counter][23:16] <= write_data_i[7:0];
                        2'b11 : cache_data[counter][31:24] <= write_data_i[7:0];
                    endcase
                end
                else begin
                    $display("sara");
                    cache_data[counter] <= write_data_i;
                end
                
                cache_tag[counter] <= tag;
                //cache_data[counter] <= write_data_i;
                valid[counter] <= 1'b1;
            end
        end
        //also add cache data 
        //cache tag
        //valid
    end
endmodule

/*note to self
if load instruction with byteop and there is a miss fetch whole word so mem_byte_op_o will be 0
but output must be correct so we need a condition for outputing the correct byte...

if load instruction with byteop and there is a hit we just use the logic from before...

if store instruction mem_byte_op_o = byte_op_i...
it doesnt matter if there is a hit or a miss we need some logic to write to the correct bits in our cache_data...
31    24 23    16 15     8 7      0
11001001 11100111 11011111 11010101


also need to make read_data_o 32'b0 for non read instructions...

00 01 10 11
00 11 01 10          
00 10 11 01    


if(byte_op_i) begin
    case(byteoffset)
        2'b00 : cache_data[set][counter][7:0] <= write_data_i[7:0];
        2'b01 : cache_data[set][counter][15:8] <= write_data_i[7:0];
        2'b10 : cache_data[set][counter][23:16] <= write_data_i[7:0];
        2'b11 : cache_data[set][counter][31:24] <= write_data_i[7:0];
    endcase
end
else begin
    cache_data[set][counter] <= write_data_i;
end
*/

cache.sv
module cache (
	input logic clk_i , write_enable_i , cache_enable_i, byte_op_i,
	input logic [31:0] address_i , write_data_i,
	//output signals
	output logic [31:0] read_data_o
);

    logic [31:0] mem_incoming_data;
    logic [31:0] mem_address, mem_write_data;
    logic mem_write_enable , mem_byte_op;

cacheline line(
    .clk_i(clk_i),
    .write_enable_i(write_enable_i),
    .cache_enable_i(cache_enable_i),
    .address_i(address_i),
    .write_data_i(write_data_i),
    .read_data_o(read_data_o),
    .byte_op_i(byte_op_i),

    .mem_incoming_data_i(mem_incoming_data),
    .mem_address_o(mem_address),
    .mem_write_data_o(mem_write_data),
    .mem_write_enable_o(mem_write_enable),
    .mem_byte_op_o(mem_byte_op)
);

data_memory memory(
    .clk_i(clk_i),
    .we_i(mem_write_enable),
    .addr_i(mem_address),
    .wd_i(mem_write_data),
    .rd_o(mem_incoming_data),
    .byte_op_i(mem_byte_op)
);

endmodule

cache.vcd
$version Generated by VerilatedVcd $end
$date Fri Dec 15 00:00:50 2023 $end
$timescale 1ps $end

 $scope module TOP $end
  $var wire 32 = address_i [31:0] $end
  $var wire  1 < byte_op_i $end
  $var wire  1 ; cache_enable_i $end
  $var wire  1 9 clk_i $end
  $var wire 32 ? read_data_o [31:0] $end
  $var wire 32 > write_data_i [31:0] $end
  $var wire  1 : write_enable_i $end
  $scope module cache $end
   $var wire 32 = address_i [31:0] $end
   $var wire  1 < byte_op_i $end
   $var wire  1 ; cache_enable_i $end
   $var wire  1 9 clk_i $end
   $var wire 32 = mem_address [31:0] $end
   $var wire  1 4 mem_byte_op $end
   $var wire 32 2 mem_incoming_data [31:0] $end
   $var wire 32 3 mem_write_data [31:0] $end
   $var wire  1 : mem_write_enable $end
   $var wire 32 ? read_data_o [31:0] $end
   $var wire 32 > write_data_i [31:0] $end
   $var wire  1 : write_enable_i $end
   $scope module line $end
    $var wire 32 = address_i [31:0] $end
    $var wire  1 < byte_op_i $end
    $var wire  2 A byteoffset [1:0] $end
    $var wire 32 % cache_data[0] [31:0] $end
    $var wire 32 & cache_data[1] [31:0] $end
    $var wire 32 ' cache_data[2] [31:0] $end
    $var wire 32 ( cache_data[3] [31:0] $end
    $var wire  1 ; cache_enable_i $end
    $var wire 30 ) cache_tag[0] [29:0] $end
    $var wire 30 * cache_tag[1] [29:0] $end
    $var wire 30 + cache_tag[2] [29:0] $end
    $var wire 30 , cache_tag[3] [29:0] $end
    $var wire  1 9 clk_i $end
    $var wire  2 1 counter [1:0] $end
    $var wire  1 5 hit $end
    $var wire 32 = mem_address_o [31:0] $end
    $var wire  1 4 mem_byte_op_o $end
    $var wire 32 2 mem_incoming_data_i [31:0] $end
    $var wire 32 3 mem_write_data_o [31:0] $end
    $var wire  1 : mem_write_enable_o $end
    $var wire 32 ? read_data_o [31:0] $end
    $var wire 30 @ tag [29:0] $end
    $var wire 32 C tag_bits [31:0] $end
    $var wire  1 - valid[0] $end
    $var wire  1 . valid[1] $end
    $var wire  1 / valid[2] $end
    $var wire  1 0 valid[3] $end
    $var wire  2 6 wayhit [1:0] $end
    $var wire 32 B width [31:0] $end
    $var wire 32 > write_data_i [31:0] $end
    $var wire  1 : write_enable_i $end
    $scope module unnamedblk1 $end
     $var wire 32 # i [31:0] $end
    $upscope $end
    $scope module unnamedblk2 $end
     $var wire 32 7 i [31:0] $end
    $upscope $end
   $upscope $end
   $scope module memory $end
    $var wire 32 D BYTE_WIDTH [31:0] $end
    $var wire 32 B DATA_WIDTH [31:0] $end
    $var wire 32 F END_ADDRESS [31:0] $end
    $var wire 32 E START_ADDRESS [31:0] $end
    $var wire 32 8 addr [31:0] $end
    $var wire 32 = addr_i [31:0] $end
    $var wire  1 4 byte_op_i $end
    $var wire  1 9 clk_i $end
    $var wire 32 2 rd_o [31:0] $end
    $var wire 32 3 wd_i [31:0] $end
    $var wire  1 : we_i $end
    $scope module unnamedblk1 $end
     $var wire 32 $ i [31:0] $end
    $upscope $end
   $upscope $end
  $upscope $end
 $upscope $end
$enddefinitions $end


#0
b00000000000000000000000000000000 #
b00000000000000000000000000000000 $
b00000000000000000000000000000000 %
b00000000000000000000000000000000 &
b00000000000000000000000000000000 '
b00000000000000000000000000000000 (
b000000000000000000000000000000 )
b000000000000000000000000000000 *
b000000000000000000000000000000 +
b000000000000000000000000000000 ,
0-
0.
0/
00
b00 1
b00000000000000000000000000000000 2
b00000000000000000000000000000000 3
04
05
b00 6
b00000000000000000000000000000000 7
b00000000000000000000000000000000 8
09
0:
0;
0<
b00000000000000000000000000000000 =
b00000000000000000000000000000000 >
b00000000000000000000000000000000 ?
b000000000000000000000000000000 @
b00 A
b00000000000000000000000000100000 B
b00000000000000000000000000011110 C
b00000000000000000000000000001000 D
b00000000000000000000000000000000 E
b00000000000000011111111111111111 F
#1
b00000000000000000000000000000100 #
b11010101110111111110011111001001 2
19
#2
09
#3
19
#4
09
#5
19
#6
09
#7
19
#8
09
1:
1;
b00000000000000000000000000100000 =
b00000000000000000000000000111011 >
b000000000000000000000000001000 @
#9
b11000001101010001010100111010001 2
b00000000000000000000000000111011 3
b00000000000000000000000000000100 7
b00000000000000000000000000100000 8
19
#10
b00000000000000000000000000111011 %
b000000000000000000000000001000 )
1-
b01 1
b00000000000000000000000000111011 2
15
b00000000000000000000000000000000 7
09
b00000000000000000000000001100000 =
b00000000000000000000000000111000 >
b000000000000000000000000011000 @
#11
b00111001001101100011101101000011 2
b00000000000000000000000000111000 3
05
b00000000000000000000000000000100 7
b00000000000000000000000001100000 8
19
#12
b00000000000000000000000000111000 &
b000000000000000000000000011000 *
1.
b10 1
b00000000000000000000000000111000 2
15
b01 6
b00000000000000000000000000000001 7
09
1<
b00000000000000000000010011010001 =
b00000000000000000000000001111011 >
b000000000000000000000100110100 @
b01 A
#13
b00000000000000000000000010010111 2
b00000000000000000000000001111011 3
14
05
b00000000000000000000000000000100 7
b00000000000000000000010011010001 8
19
#14
b00000000000000000111101100000000 '
b000000000000000000000100110100 +
1/
b11 1
b00000000000000000000000001111011 2
15
b10 6
b00000000000000000000000000000010 7
09
0;
