testing/data_memory.sv
module data_memory # (
    parameter DATA_WIDTH    = 32,
              BYTE_WIDTH    = 8, 
              START_ADDRESS = 32'h10000,
              END_ADDRESS   = 17'h1FFFF
)(
    input  logic                        clk_i, we_i, byte_op_i,
    input  logic [DATA_WIDTH-1:0]       addr_i,
    input  logic [DATA_WIDTH-1:0]       wd_i,
    output logic [DATA_WIDTH-1:0]       rd_o
);

logic [BYTE_WIDTH-1:0]  data_ram [END_ADDRESS:0];
logic [DATA_WIDTH-1:0]  addr;

assign addr = byte_op_i ? addr_i : (addr_i & 32'hFFFFFFFC);

initial begin
    $readmemh("gaussian.mem", data_ram, START_ADDRESS, START_ADDRESS+7);
    for (int i = 0; i < START_ADDRESS; i++) begin
        data_ram[i] = {BYTE_WIDTH{1'b0}};
    end
end

always_comb begin
    case (byte_op_i)
        1'b0: rd_o = {data_ram[addr+3], data_ram[addr+2], data_ram[addr+1], data_ram[addr+0]};
        1'b1: rd_o = {{3*BYTE_WIDTH{1'b0}}, data_ram[addr]};    // only implementing LBU
        default: rd_o = {DATA_WIDTH{1'b0}};
    endcase
end

always_ff @(negedge clk_i) begin

    if (we_i) begin
        data_ram[addr] <= wd_i[BYTE_WIDTH-1:0];

        if (!byte_op_i) begin
            data_ram[addr+1] <= wd_i[2*BYTE_WIDTH-1:BYTE_WIDTH];
            data_ram[addr+2] <= wd_i[3*BYTE_WIDTH-1:2*BYTE_WIDTH];
            data_ram[addr+3] <= wd_i[4*BYTE_WIDTH-1:3*BYTE_WIDTH];
        end
    end
end

endmodule

testing/cacheline.sv

module cacheline #(
    parameter   width = 32,
			 	tag_bits = 30
               // BYTE_WIDTH = 8
)(
	input logic clk_i, write_enable_i, cache_enable_i, byte_op_i,
	input logic [width-1:0] address_i , write_data_i,
	//output signals
	output logic [width-1:0] read_data_o,
	//memory interface signals
	input logic [width-1:0] mem_incoming_data_i,
	output logic [width-1:0] mem_address_o , mem_write_data_o,
	output logic mem_write_enable_o , mem_byte_op_o
);
//--------------------------data_structure---------------------------

	logic [width-1:0] cache_data[3:0];
	logic [tag_bits-1:0] cache_tag [3:0];
	logic valid [3:0];
    logic [1:0] counter;
//------------------------internal_signals----------------------------
    logic [tag_bits-1 :0] tag;
    logic [1:0] byteoffset;
    logic hit;
    logic [1:0] wayhit;

//-------------------------assign_values--------------------------------
    assign tag = address_i[31:2];
    assign mem_byte_op_o = 1'b0;
    assign byteoffset = address_i[1:0];
    assign mem_address_o = address_i;
    assign mem_write_enable_o = write_enable_i;
//----------------------------------------------------------------------
    initial begin
        hit = 1'b0;
        for(int i = 0 ; i<4 ; i++) begin
            valid[i[1:0]] = 1'b0;
            cache_data[i[1:0]] = 32'b0;
            cache_tag [i[1:0]] = 30'b0;
        end
    end

    always_comb begin
        if(cache_enable_i) begin
            
            //load word
            if(!write_enable_i) begin
                mem_byte_op_o = 0;
                //mem_write_enable_o <= 1'b0;
                if(hit) begin
                    if(byte_op_i)begin
                        case(byteoffset)
                        2'b00 : read_data_o = { {24'b0},mem_incoming_data_i[7:0]};
                        2'b01 : read_data_o = { {24'b0},mem_incoming_data_i[15:8]};
                        2'b10 : read_data_o = { {24'b0},mem_incoming_data_i[23:16]};
                        2'b11 : read_data_o = { {24'b0},mem_incoming_data_i[31:24]};
                        endcase
                    end
                    else begin
                        read_data_o = cache_data[wayhit];   
                    end
                end
                else begin
                    //counter = counter + 1'b1;
                    if(byte_op_i)begin
                        case(byteoffset)
                        2'b00 : read_data_o = { {24'b0},mem_incoming_data_i[7:0]};
                        2'b01 : read_data_o = { {24'b0},mem_incoming_data_i[15:8]};
                        2'b10 : read_data_o = { {24'b0},mem_incoming_data_i[23:16]};
                        2'b11 : read_data_o = { {24'b0},mem_incoming_data_i[31:24]};
                        endcase
                    end
                    else begin
                    //mem_address_o <= address_i;
                        read_data_o = mem_incoming_data_i;
                    end
                end
            end
            //store word
            else begin
                //counter = counter + 1'b1;
                mem_byte_op_o = byte_op_i;
                //mem_address_o <= address_i;
                //mem_write_enable_o <= 1'b1;
                if(hit) begin

                    mem_write_data_o = write_data_i;
                end
                else begin
                    // cache_tag[counter] = tag;
                    // cache_data[counter] = write_data_i;
                    // valid[counter] = 1'b1;
                    mem_write_data_o = write_data_i;
                end
            end
        end
    end

    always_ff@(negedge clk_i) begin
        if (cache_enable_i==1'b1)begin
            //check for tag match
            for(int i = 0 ; i < 4 ; i++) begin
                if(cache_tag[i[1:0]] == tag) begin
                    hit <= valid[i[1:0]];
                    wayhit <= i[1:0];
                    break;
                end
                else
                    hit <= 1'b0;
            end
            
            if((write_enable_i==1'b1) || (hit==1'b0)) begin
                counter <= counter + 1'b1;
            end
            if((write_enable_i == 1'b0) && (hit==1'b0))begin //load word and not in cache
                cache_data[counter] <= mem_incoming_data_i;
                cache_tag[counter] <= tag;
                //cache_data[counter] <= mem_incoming_data_i;
                valid[counter] <= 1'b1;
            end
            else if((write_enable_i==1'b1) &&(hit==1'b1)) begin
                if(byte_op_i) begin
                    case(byteoffset)
                        2'b00 : cache_data[wayhit][7:0] <= write_data_i[7:0];
                        2'b01 : cache_data[wayhit][15:8] <= write_data_i[7:0];
                        2'b10 : cache_data[wayhit][23:16] <= write_data_i[7:0];
                        2'b11 : cache_data[wayhit][31:24] <= write_data_i[7:0];
                    endcase
                end
                else begin
                    
                    cache_data[wayhit] <= write_data_i;
                end
                //cache_tag[wayhit] <= tag;
                //cache_data[wayhit] <= write_data_i;
                valid[wayhit] <= 1'b1;
            end
            else if((write_enable_i==1'b1)&& (hit==1'b0))begin
                if(byte_op_i) begin
                    case(byteoffset)
                        2'b00 : cache_data[counter][7:0] <= write_data_i[7:0];
                        2'b01 : cache_data[counter][15:8] <= write_data_i[7:0];
                        2'b10 : cache_data[counter][23:16] <= write_data_i[7:0];
                        2'b11 : cache_data[counter][31:24] <= write_data_i[7:0];
                    endcase
                end
                else begin
                    cache_data[counter] <= write_data_i;
                end
                
                cache_tag[counter] <= tag;
                //cache_data[counter] <= write_data_i;
                valid[counter] <= 1'b1;
            end
        end
        //also add cache data 
        //cache tag
        //valid
    end
endmodule

/*note to self
if load instruction with byteop and there is a miss fetch whole word so mem_byte_op_o will be 0
but output must be correct so we need a condition for outputing the correct byte...

if load instruction with byteop and there is a hit we just use the logic from before...

if store instruction mem_byte_op_o = byte_op_i...
it doesnt matter if there is a hit or a miss we need some logic to write to the correct bits in our cache_data...
31    24 23    16 15     8 7      0
11001001 11100111 11011111 11010101


also need to make read_data_o 32'b0 for non read instructions...

00 01 10 11
00 11 01 10          
00 10 11 01    


if(byte_op_i) begin
    case(byteoffset)
        2'b00 : cache_data[set][counter][7:0] <= write_data_i[7:0];
        2'b01 : cache_data[set][counter][15:8] <= write_data_i[7:0];
        2'b10 : cache_data[set][counter][23:16] <= write_data_i[7:0];
        2'b11 : cache_data[set][counter][31:24] <= write_data_i[7:0];
    endcase
end
else begin
    cache_data[set][counter] <= write_data_i;
end
*/

cache.sv
module cache (
	input logic clk_i , we_i , byte_op_i, //cache_enable_i,
	input logic [31:0] addr_i , wd_i,
	//output signals
	output logic [31:0] rd_o
);

    logic [31:0] mem_incoming_data;
    logic [31:0] mem_address, mem_write_data;
    logic mem_write_enable , mem_byte_op;


cacheline line(
    .clk_i(clk_i),
    .write_enable_i(we_i),
    .cache_enable_i(1'b1),
    .address_i(addr_i),
    .write_data_i(wd_i),
    .read_data_o(rd_o),
    .byte_op_i(byte_op_i),

    .mem_incoming_data_i(mem_incoming_data),
    .mem_address_o(mem_address),
    .mem_write_data_o(mem_write_data),
    .mem_write_enable_o(mem_write_enable),
    .mem_byte_op_o(mem_byte_op)
);

data_memory memory(
    .clk_i(clk_i),
    .we_i(mem_write_enable),
    .addr_i(mem_address),
    .wd_i(mem_write_data),
    .rd_o(mem_incoming_data),
    .byte_op_i(mem_byte_op)
);

endmodule

testing/cache.vcd
$version Generated by VerilatedVcd $end
$date Fri Dec 15 06:59:04 2023 $end
$timescale 1ps $end

 $scope module TOP $end
  $var wire 32 < addr_i [31:0] $end
  $var wire  1 ; byte_op_i $end
  $var wire  1 9 clk_i $end
  $var wire 32 > rd_o [31:0] $end
  $var wire 32 = wd_i [31:0] $end
  $var wire  1 : we_i $end
  $scope module cache $end
   $var wire 32 < addr_i [31:0] $end
   $var wire  1 ; byte_op_i $end
   $var wire  1 9 clk_i $end
   $var wire 32 < mem_address [31:0] $end
   $var wire  1 7 mem_byte_op $end
   $var wire 32 5 mem_incoming_data [31:0] $end
   $var wire 32 6 mem_write_data [31:0] $end
   $var wire  1 : mem_write_enable $end
   $var wire 32 > rd_o [31:0] $end
   $var wire 32 = wd_i [31:0] $end
   $var wire  1 : we_i $end
   $scope module line $end
    $var wire 32 < address_i [31:0] $end
    $var wire  1 ; byte_op_i $end
    $var wire  2 @ byteoffset [1:0] $end
    $var wire 32 % cache_data[0] [31:0] $end
    $var wire 32 & cache_data[1] [31:0] $end
    $var wire 32 ' cache_data[2] [31:0] $end
    $var wire 32 ( cache_data[3] [31:0] $end
    $var wire  1 C cache_enable_i $end
    $var wire 30 ) cache_tag[0] [29:0] $end
    $var wire 30 * cache_tag[1] [29:0] $end
    $var wire 30 + cache_tag[2] [29:0] $end
    $var wire 30 , cache_tag[3] [29:0] $end
    $var wire  1 9 clk_i $end
    $var wire  2 1 counter [1:0] $end
    $var wire  1 2 hit $end
    $var wire 32 < mem_address_o [31:0] $end
    $var wire  1 7 mem_byte_op_o $end
    $var wire 32 5 mem_incoming_data_i [31:0] $end
    $var wire 32 6 mem_write_data_o [31:0] $end
    $var wire  1 : mem_write_enable_o $end
    $var wire 32 > read_data_o [31:0] $end
    $var wire 30 ? tag [29:0] $end
    $var wire 32 B tag_bits [31:0] $end
    $var wire  1 - valid[0] $end
    $var wire  1 . valid[1] $end
    $var wire  1 / valid[2] $end
    $var wire  1 0 valid[3] $end
    $var wire  2 3 wayhit [1:0] $end
    $var wire 32 A width [31:0] $end
    $var wire 32 = write_data_i [31:0] $end
    $var wire  1 : write_enable_i $end
    $scope module unnamedblk1 $end
     $var wire 32 # i [31:0] $end
    $upscope $end
    $scope module unnamedblk2 $end
     $var wire 32 4 i [31:0] $end
    $upscope $end
   $upscope $end
   $scope module memory $end
    $var wire 32 D BYTE_WIDTH [31:0] $end
    $var wire 32 A DATA_WIDTH [31:0] $end
    $var wire 17 F END_ADDRESS [16:0] $end
    $var wire 32 E START_ADDRESS [31:0] $end
    $var wire 32 8 addr [31:0] $end
    $var wire 32 < addr_i [31:0] $end
    $var wire  1 7 byte_op_i $end
    $var wire  1 9 clk_i $end
    $var wire 32 5 rd_o [31:0] $end
    $var wire 32 6 wd_i [31:0] $end
    $var wire  1 : we_i $end
    $scope module unnamedblk1 $end
     $var wire 32 $ i [31:0] $end
    $upscope $end
   $upscope $end
  $upscope $end
 $upscope $end
$enddefinitions $end


#0
b00000000000000000000000000000000 #
b00000000000000000000000000000000 $
b00000000000000000000000000000000 %
b00000000000000000000000000000000 &
b00000000000000000000000000000000 '
b00000000000000000000000000000000 (
b000000000000000000000000000000 )
b000000000000000000000000000000 *
b000000000000000000000000000000 +
b000000000000000000000000000000 ,
0-
0.
0/
00
b00 1
02
b00 3
b00000000000000000000000000000000 4
b00000000000000000000000000000000 5
b00000000000000000000000000000000 6
07
b00000000000000000000000000000000 8
19
0:
0;
b00000000000000000000000000000000 <
b00000000000000000000000000000000 =
b00000000000000000000000000000000 >
b000000000000000000000000000000 ?
b00 @
b00000000000000000000000000100000 A
b00000000000000000000000000011110 B
1C
b00000000000000000000000000001000 D
b00000000000000010000000000000000 E
b11111111111111111 F
#1
b00000000000000000000000000000100 #
b00000000000000010000000000000000 $
09
#2
b00111100010011110100001001010101 5
b00000000000000000000000001011111 6
b00000000000000010000000000000000 8
19
1:
b00000000000000010000000000000010 <
b00000000000000000000000001011111 =
b000000000000000100000000000000 ?
b10 @
#3
b00000000000000000000000001011111 %
b000000000000000100000000000000 )
1-
b01 1
b00000000000000000000000000000100 4
b00000000000000000000000001011111 5
09
#4
b10111001000110000001101001010000 5
b00000000000000000000000001110010 6
b00000000000000010000000000000100 8
19
b00000000000000010000000000000110 <
b00000000000000000000000001110010 =
b000000000000000100000000000001 ?
#5
b00000000000000000000000001110010 &
b000000000000000100000000000001 *
1.
b10 1
b00000000000000000000000001110010 5
09
#6
b00000000000000000000000000000000 5
b00000000000000000000000001011111 6
17
b00000000000000010000000000000110 8
19
1;
b00000000000000000000000001011111 =
#7
b00000000010111110000000000000000 '
b000000000000000100000000000001 +
1/
b11 1
12
b01 3
b00000000000000000000000000000001 4
b00000000000000000000000001011111 5
09
#8
b00000000010111110000000001110010 5
07
b00000000000000010000000000000100 8
19
0:
0;
b00000000000000000000000011000001 =
b00000000000000000000000001110010 >
#9
09
#10
b00000000000000000000000000000000 5
b00000000000000000000000011001010 6
17
b00000000000000010000000000000010 8
19
1:
1;
b00000000000000010000000000000010 <
b00000000000000000000000011001010 =
b000000000000000100000000000000 ?
#11
b00000000110010100000000001110010 &
b00 1
b00 3
b00000000000000000000000000000000 4
b00000000000000000000000011001010 5
09
#12
b00000000110010100000000001011111 5
07
b00000000000000010000000000000000 8
19
0:
b00000000000000010000000000000001 <
b00000000000000000000000011000100 =
b00000000000000000000000000000000 >
b01 @
#13
09
#14
b00000000010111110000000001110010 5
b00000000000000010000000000000100 8
19
0;
b00000000000000010000000000000100 <
b00000000000000000000000001010000 =
b00000000000000000000000001011111 >
b000000000000000100000000000001 ?
b00 @
#15
b01 3
b00000000000000000000000000000001 4
09
b00000000110010100000000001110010 >
#16
b00000000000000000000000000000000 5
b00000000000000000000000000110001 6
17
b00000000000000010000000000000111 8
19
1:
1;
b00000000000000010000000000000111 <
b00000000000000000000000000110001 =
b11 @
#17
b00110001110010100000000001110010 &
b01 1
b00000000000000000000000000110001 5
09
#18
b00000000110010100000000001011111 5
b00000000000000000000000010000001 6
07
b00000000000000010000000000000000 8
19
0;
b00000000000000010000000000000011 <
b00000000000000000000000010000001 =
b000000000000000100000000000000 ?
#19
b00000000000000000000000010000001 &
b10 1
b00 3
b00000000000000000000000000000000 4
b00000000000000000000000010000001 5
09
#20
b00110001010111110000000001110010 5
b00000000000000010000000000000100 8
19
0:
b00000000000000010000000000000111 <
b00000000000000000000000001100101 =
b00000000000000000000000001011111 >
b000000000000000100000000000001 ?
#21
b01 3
b00000000000000000000000000000001 4
09
b00000000000000000000000010000001 >
#22
b00000000000000000000000000110101 6
19
1:
b00000000000000000000000000110101 =
#23
b00000000000000000000000000110101 &
b11 1
b00000000000000000000000000110101 5
09
#24
19
0:
b00000000000000010000000000000101 <
b00000000000000000000000011111111 =
b00000000000000000000000000110101 >
b01 @
#25
09
#26
b00000000000000000000000000000000 5
b00000000000000000000000010110110 6
17
b00000000000000010000000000000101 8
19
1:
1;
b00000000000000000000000010110110 =
#27
b00000000000000001011011000110101 &
b00 1
b00000000000000000000000010110110 5
09
#28
b00000000000000000000000010000001 5
b00000000000000000000000000001111 6
07
b00000000000000010000000000000000 8
19
0;
b00000000000000010000000000000011 <
b00000000000000000000000000001111 =
b000000000000000100000000000000 ?
b11 @
#29
b00000000000000000000000000001111 &
b01 1
b00 3
b00000000000000000000000000000000 4
b00000000000000000000000000001111 5
09
#30
19
0:
1;
b00000000000000000000000000111010 =
b00000000000000000000000000000000 >
#31
09
#32
19
b00000000000000010000000000000000 <
b00000000000000000000000001001011 =
b00000000000000000000000000001111 >
b00 @
#33
09
#34
b00000000000000001011011000110101 5
b00000000000000000000000001111011 6
b00000000000000010000000000000100 8
19
1:
0;
b00000000000000010000000000000100 <
b00000000000000000000000001111011 =
b000000000000000100000000000001 ?
#35
b00000000000000000000000001111011 %
b10 1
b01 3
b00000000000000000000000000000001 4
b00000000000000000000000001111011 5
09
#36
19
0:
b00000000000000010000000000000110 <
b00000000000000000000000011011101 =
b10 @
#37
09
#38
b00000000000000000000000000000000 5
b00000000000000000000000011000111 6
17
b00000000000000010000000000000001 8
19
1:
1;
b00000000000000010000000000000001 <
b00000000000000000000000011000111 =
b000000000000000100000000000000 ?
b01 @
#39
b00000000000000001100011100001111 &
b11 1
b00 3
b00000000000000000000000000000000 4
b00000000000000000000000011000111 5
09
