testing/data_memory.sv
module data_memory # (
    parameter DATA_WIDTH    = 32,
              BYTE_WIDTH    = 8, 
              START_ADDRESS = 32'h10000,
              END_ADDRESS   = 17'h1FFFF
)(
    input  logic                        clk_i, we_i, byte_op_i,
    input  logic [DATA_WIDTH-1:0]       addr_i,
    input  logic [DATA_WIDTH-1:0]       wd_i,
    output logic [DATA_WIDTH-1:0]       rd_o
);

logic [BYTE_WIDTH-1:0]  data_ram [END_ADDRESS:0];
logic [DATA_WIDTH-1:0]  addr;

assign addr = byte_op_i ? addr_i : (addr_i & 32'hFFFFFFFC);

initial begin
    $readmemh("gaussian.mem", data_ram, START_ADDRESS, START_ADDRESS+7);
    for (int i = 0; i < START_ADDRESS; i++) begin
        data_ram[i] = {BYTE_WIDTH{1'b0}};
    end
end

always_comb begin
    case (byte_op_i)
        1'b0: rd_o = {data_ram[addr+3], data_ram[addr+2], data_ram[addr+1], data_ram[addr+0]};
        1'b1: rd_o = {{3*BYTE_WIDTH{1'b0}}, data_ram[addr]};    // only implementing LBU
        default: rd_o = {DATA_WIDTH{1'b0}};
    endcase
end

always_ff @(negedge clk_i) begin

    if (we_i) begin
        data_ram[addr] <= wd_i[BYTE_WIDTH-1:0];

        if (!byte_op_i) begin
            data_ram[addr+1] <= wd_i[2*BYTE_WIDTH-1:BYTE_WIDTH];
            data_ram[addr+2] <= wd_i[3*BYTE_WIDTH-1:2*BYTE_WIDTH];
            data_ram[addr+3] <= wd_i[4*BYTE_WIDTH-1:3*BYTE_WIDTH];
        end
    end
end

endmodule

testing/data_memory.vcd
$version Generated by VerilatedVcd $end
$date Fri Dec 15 05:06:03 2023 $end
$timescale 1ps $end

 $scope module TOP $end
  $var wire 32 ' addr_i [31:0] $end
  $var wire  1 & byte_op_i $end
  $var wire  1 $ clk_i $end
  $var wire 32 ) rd_o [31:0] $end
  $var wire 32 ( wd_i [31:0] $end
  $var wire  1 % we_i $end
  $scope module data_memory $end
   $var wire 32 , BYTE_WIDTH [31:0] $end
   $var wire 32 + DATA_WIDTH [31:0] $end
   $var wire 17 . END_ADDRESS [16:0] $end
   $var wire 32 - START_ADDRESS [31:0] $end
   $var wire 32 * addr [31:0] $end
   $var wire 32 ' addr_i [31:0] $end
   $var wire  1 & byte_op_i $end
   $var wire  1 $ clk_i $end
   $var wire 32 ) rd_o [31:0] $end
   $var wire 32 ( wd_i [31:0] $end
   $var wire  1 % we_i $end
   $scope module unnamedblk1 $end
    $var wire 32 # i [31:0] $end
   $upscope $end
  $upscope $end
 $upscope $end
$enddefinitions $end


#0
b00000000000000000000000000000000 #
1$
0%
0&
b00000000000000000000000000000000 '
b00000000000000000000000000000000 (
b00000000000000000000000000000000 )
b00000000000000000000000000000000 *
b00000000000000000000000000100000 +
b00000000000000000000000000001000 ,
b00000000000000010000000000000000 -
b11111111111111111 .
#1
b00000000000000010000000000000000 #
0$
#2
1$
1&
b00000000000000010000000000000111 '
b00000000000000000000000001100100 (
b00000000000000000000000011011010 )
b00000000000000010000000000000111 *
#3
0$
#4
1$
1%
b00000000000000010000000000000000 '
b00000000000000000000000000010101 (
b00000000000000000000000011001001 )
b00000000000000010000000000000000 *
#5
0$
b00000000000000000000000000010101 )
#6
1$
0&
b00000000000000010000000000000001 '
b00000000000000000000000011010000 (
b11010101110111111110011100010101 )
#7
0$
b00000000000000000000000011010000 )
#8
1$
1&
b00000000000000010000000000000100 '
b00000000000000000000000001100000 (
b00000000000000000000000011101101 )
b00000000000000010000000000000100 *
#9
0$
b00000000000000000000000001100000 )
#10
1$
b00000000000000010000000000000101 '
b00000000000000000000000000001001 (
b00000000000000000000000011001101 )
b00000000000000010000000000000101 *
#11
0$
b00000000000000000000000000001001 )
#12
1$
0&
b00000000000000010000000000000110 '
b00000000000000000000000000110011 (
b11011010110101010000100101100000 )
b00000000000000010000000000000100 *
#13
0$
b00000000000000000000000000110011 )
#14
1$
b00000000000000010000000000000011 '
b00000000000000000000000011000110 (
b00000000000000000000000011010000 )
b00000000000000010000000000000000 *
#15
0$
b00000000000000000000000011000110 )
#16
1$
0%
1&
b00000000000000000000000010101010 (
b00000000000000000000000000000000 )
b00000000000000010000000000000011 *
#17
0$
#18
1$
b00000000000000010000000000000100 '
b00000000000000000000000001110100 (
b00000000000000000000000000110011 )
b00000000000000010000000000000100 *
#19
0$
#20
1$
b00000000000000010000000000000111 '
b00000000000000000000000001011001 (
b00000000000000000000000000000000 )
b00000000000000010000000000000111 *
#21
0$
#22
1$
b00000000000000010000000000000001 '
b00000000000000000000000010000110 (
b00000000000000010000000000000001 *
#23
0$
#24
1$
1%
0&
b00000000000000010000000000000111 '
b00000000000000000000000000111101 (
b00000000000000000000000000110011 )
b00000000000000010000000000000100 *
#25
0$
b00000000000000000000000000111101 )
#26
1$
b00000000000000010000000000000100 '
b00000000000000000000000001111011 (
#27
0$
b00000000000000000000000001111011 )
#28
1$
0%
b00000000000000010000000000000010 '
b00000000000000000000000001100110 (
b00000000000000000000000011000110 )
b00000000000000010000000000000000 *
#29
0$
#30
1$
b00000000000000010000000000000110 '
b00000000000000000000000010110001 (
b00000000000000000000000001111011 )
b00000000000000010000000000000100 *
#31
0$
#32
1$
1&
b00000000000000010000000000000010 '
b00000000000000000000000001001110 (
b00000000000000000000000000000000 )
b00000000000000010000000000000010 *
#33
0$
#34
1$
b00000000000000000000000011111010 (
#35
0$
#36
1$
b00000000000000010000000000000000 '
b00000000000000000000000010000010 (
b00000000000000000000000011000110 )
b00000000000000010000000000000000 *
#37
0$
#38
1$
0&
b00000000000000010000000000000100 '
b00000000000000000000000000100100 (
b00000000000000000000000001111011 )
b00000000000000010000000000000100 *
