project/alu/alu.sv
module alu#(
    parameter DATA_WIDTH = 32
)(
    input  logic [DATA_WIDTH-1:0] SrcA, SrcB,
    input  logic [2:0] ALUControl,
    output logic [DATA_WIDTH-1:0] ALUResult,
    output logic EQ
);

always_comb begin 
    EQ = (SrcA == SrcB);
    case (ALUControl)
        // add
        3'b000: ALUResult = SrcA + SrcB;
        // subtract
        3'b001: ALUResult = SrcA - SrcB;
        // and
        3'b010: ALUResult = SrcA & SrcB;
        // or
        3'b011: ALUResult = SrcA | SrcB;
        // SLT
        3'b101: ALUResult = {{DATA_WIDTH-1{1'b0}}, (SrcA < SrcB)};
        default: ALUResult = {DATA_WIDTH{1'b0}};
    endcase 
end

endmodule

project/alu/alu.vcd
$version Generated by VerilatedVcd $end
$date Sun Nov 26 07:56:18 2023 $end
$timescale 1ps $end

 $scope module TOP $end
  $var wire  3 % ALUControl [2:0] $end
  $var wire 32 & ALUResult [31:0] $end
  $var wire  1 ' EQ $end
  $var wire 32 # SrcA [31:0] $end
  $var wire 32 $ SrcB [31:0] $end
  $scope module alu $end
   $var wire  3 % ALUControl [2:0] $end
   $var wire 32 & ALUResult [31:0] $end
   $var wire 32 ( DATA_WIDTH [31:0] $end
   $var wire  1 ' EQ $end
   $var wire 32 # SrcA [31:0] $end
   $var wire 32 $ SrcB [31:0] $end
  $upscope $end
 $upscope $end
$enddefinitions $end


#0
b00000000000000000000000000000000 #
b00000000000000000000000000000000 $
b000 %
b00000000000000000000000000000000 &
0'
b00000000000000000000000000100000 (
#1
#2
b00000000000000000000000000001011 #
b00000000000000000000000000110011 $
b101 %
b00000000000000000000000000000001 &
#3
#4
b00000000000000000000000001010010 #
b010 %
b00000000000000000000000000010010 &
#5
#6
b00000000000000000000000001001001 #
b00000000000000000000000000111111 $
b001 %
b00000000000000000000000000001010 &
#7
#8
b00000000000000000000000001011011 #
b00000000000000000000000000100111 $
b000 %
b00000000000000000000000010000010 &
#9
#10
b00000000000000000000000000101101 #
b00000000000000000000000000101100 $
b011 %
b00000000000000000000000000101101 &
#11
#12
b00000000000000000000000001100001 #
b00000000000000000000000000111011 $
b000 %
b00000000000000000000000010011100 &
#13
#14
b00000000000000000000000000010111 #
b00000000000000000000000000100000 $
b011 %
b00000000000000000000000000110111 &
#15
#16
b00000000000000000000000000101010 #
b00000000000000000000000000101001 $
b00000000000000000000000000101011 &
#17
#18
b00000000000000000000000000001111 #
b00000000000000000000000000000000 $
b101 %
b00000000000000000000000000000000 &
#19
#20
b00000000000000000000000001010000 #
b00000000000000000000000000100101 $
b000 %
b00000000000000000000000001110101 &
#21
#22
b00000000000000000000000001100010 #
b00000000000000000000000000110000 $
b011 %
b00000000000000000000000001110010 &
#23
#24
b00000000000000000000000001011001 #
b00000000000000000000000001010010 $
b101 %
b00000000000000000000000000000000 &
#25
#26
b00000000000000000000000000010110 #
b00000000000000000000000000111000 $
b00000000000000000000000000000001 &
#27
#28
b00000000000000000000000000001010 #
b00000000000000000000000001100011 $
b000 %
b00000000000000000000000001101101 &
#29
#30
b00000000000000000000000001001011 #
b00000000000000000000000000101100 $
b00000000000000000000000001110111 &
#31
#32
b00000000000000000000000001100000 #
b00000000000000000000000000101010 $
b001 %
b00000000000000000000000000110110 &
#33
#34
b00000000000000000000000000111000 #
b00000000000000000000000000010001 $
b011 %
b00000000000000000000000000111001 &
#35
#36
b00000000000000000000000001010000 #
b00000000000000000000000000111011 $
b010 %
b00000000000000000000000000010000 &
#37
#38
b00000000000000000000000001001011 $
b00000000000000000000000001000000 &
