project/alu/alu.sv
module alu#(
    parameter DATA_WIDTH = 32
)(
    input  logic [DATA_WIDTH-1:0] SrcA, SrcB,
    input  logic [2:0] ALUControl,
    output logic [DATA_WIDTH-1:0] ALUResult,
    output logic EQ
);

always_comb begin 
    EQ = (SrcA == SrcB);
    case (ALUControl)
        // add
        3'b000: ALUResult = SrcA + SrcB;
        // subtract
        3'b001: ALUResult = SrcA - SrcB;
        // and
        3'b010: ALUResult = SrcA & SrcB;
        // or
        3'b011: ALUResult = SrcA | SrcB;
        // SLT
        3'b101: ALUResult = {{DATA_WIDTH-1{1'b0}}, (SrcA < SrcB)};
        default: ALUResult = {DATA_WIDTH{1'b0}};
    endcase 
end

endmodule

project/alu/alu.vcd
$version Generated by VerilatedVcd $end
$timescale 1ps $end

 $scope module TOP $end
  $var wire  3 % ALUControl [2:0] $end
  $var wire 32 & ALUResult [31:0] $end
  $var wire  1 ' EQ $end
  $var wire 32 # SrcA [31:0] $end
  $var wire 32 $ SrcB [31:0] $end
  $scope module alu $end
   $var wire  3 % ALUControl [2:0] $end
   $var wire 32 & ALUResult [31:0] $end
   $var wire 32 ( DATA_WIDTH [31:0] $end
   $var wire  1 ' EQ $end
   $var wire 32 # SrcA [31:0] $end
   $var wire 32 $ SrcB [31:0] $end
  $upscope $end
 $upscope $end
$enddefinitions $end


#0
b00000000000000000000000000000000 #
b00000000000000000000000000000000 $
b000 %
b00000000000000000000000000000000 &
0'
b00000000000000000000000000100000 (
#1
1'
#2
b00000000000000000000000000101000 #
b00000000000000000000000001001011 $
b101 %
#3
b00000000000000000000000000000001 &
0'
#4
b00000000000000000000000001000101 #
b00000000000000000000000001000100 $
b001 %
#5
#6
b00000000000000000000000001001100 #
b00000000000000000000000001010011 $
b010 %
#7
b00000000000000000000000001000000 &
#8
b00000000000000000000000000101100 #
b00000000000000000000000000101011 $
#9
b00000000000000000000000000101000 &
#10
b00000000000000000000000001010001 #
b00000000000000000000000000000100 $
b001 %
#11
b00000000000000000000000001001101 &
#12
b00000000000000000000000001011010 #
b00000000000000000000000000110000 $
b010 %
#13
b00000000000000000000000000010000 &
#14
b00000000000000000000000000110110 #
b00000000000000000000000001000111 $
b000 %
#15
b00000000000000000000000001111101 &
#16
b00000000000000000000000000001011 #
b00000000000000000000000000110101 $
b001 %
#17
b11111111111111111111111111010110 &
#18
b00000000000000000000000000100100 #
b00000000000000000000000000010100 $
b010 %
#19
b00000000000000000000000000000100 &
#20
b00000000000000000000000001010010 #
b00000000000000000000000000111011 $
b000 %
#21
b00000000000000000000000010001101 &
#22
b00000000000000000000000001001101 $
b001 %
#23
b00000000000000000000000000000101 &
#24
b00000000000000000000000000100011 #
b00000000000000000000000001001111 $
b101 %
#25
b00000000000000000000000000000001 &
#26
b00000000000000000000000000111100 #
b00000000000000000000000000101101 $
b001 %
#27
b00000000000000000000000000001111 &
#28
b00000000000000000000000000011110 #
b00000000000000000000000001010011 $
b010 %
#29
b00000000000000000000000000010010 &
#30
b00000000000000000000000000001000 #
b00000000000000000000000000010101 $
b000 %
#31
b00000000000000000000000000011101 &
#32
b00000000000000000000000000011000 #
b00000000000000000000000000001000 $
b001 %
#33
b00000000000000000000000000010000 &
#34
b00000000000000000000000000101101 #
b00000000000000000000000000000111 $
b011 %
#35
b00000000000000000000000000101111 &
#36
b00000000000000000000000001100000 #
b00000000000000000000000000001111 $
b001 %
#37
b00000000000000000000000001010001 &
#38
b00000000000000000000000000000111 #
b00000000000000000000000000000010 $
b010 %
#39
b00000000000000000000000000000010 &
