project/alu/alu.sv
module alu#(
    parameter DATA_WIDTH = 32
)(
    input  logic [DATA_WIDTH-1:0] SrcA, SrcB,
    input  logic [2:0] ALUControl,
    output logic [DATA_WIDTH-1:0] ALUResult,
    output logic EQ
);

always_comb begin 
    EQ = (SrcA == SrcB);
    case (ALUControl)
        // add
        3'b000: ALUResult = SrcA + SrcB;
        // subtract
        3'b001: ALUResult = SrcA - SrcB;
        // and
        3'b010: ALUResult = SrcA & SrcB;
        // or
        3'b011: ALUResult = SrcA | SrcB;
        // SLT
        3'b101: ALUResult = {{DATA_WIDTH-1{1'b0}}, (SrcA < SrcB)};
        default: ALUResult = {DATA_WIDTH{1'b0}};
    endcase 
end

endmodule

project/alu/alu.vcd
$version Generated by VerilatedVcd $end
$date Sun Nov 26 08:04:44 2023 $end
$timescale 1ps $end

 $scope module TOP $end
  $var wire  3 % ALUControl [2:0] $end
  $var wire 32 & ALUResult [31:0] $end
  $var wire  1 ' EQ $end
  $var wire 32 # SrcA [31:0] $end
  $var wire 32 $ SrcB [31:0] $end
  $scope module alu $end
   $var wire  3 % ALUControl [2:0] $end
   $var wire 32 & ALUResult [31:0] $end
   $var wire 32 ( DATA_WIDTH [31:0] $end
   $var wire  1 ' EQ $end
   $var wire 32 # SrcA [31:0] $end
   $var wire 32 $ SrcB [31:0] $end
  $upscope $end
 $upscope $end
$enddefinitions $end


#0
b00000000000000000000000000000000 #
b00000000000000000000000000000000 $
b000 %
b00000000000000000000000000000000 &
0'
b00000000000000000000000000100000 (
#1
#2
b00000000000000000000000000010011 #
b00000000000000000000000000100000 $
b001 %
b11111111111111111111111111110011 &
#3
#4
b00000000000000000000000000010100 #
b00000000000000000000000000100001 $
b010 %
b00000000000000000000000000000000 &
#5
#6
b00000000000000000000000000011111 #
b00000000000000000000000000110101 $
b011 %
b00000000000000000000000000111111 &
#7
#8
b00000000000000000000000000111111 #
b00000000000000000000000000011110 $
b001 %
b00000000000000000000000000100001 &
#9
#10
b00000000000000000000000001011101 #
b00000000000000000000000001100000 $
b000 %
b00000000000000000000000010111101 &
#11
#12
b00000000000000000000000000011001 #
b00000000000000000000000000011111 $
b00000000000000000000000000111000 &
#13
#14
b00000000000000000000000000111110 #
b00000000000000000000000000000010 $
b011 %
b00000000000000000000000000111110 &
#15
#16
b00000000000000000000000000000100 #
b00000000000000000000000000111011 $
b00000000000000000000000000111111 &
#17
#18
b00000000000000000000000000110111 #
b00000000000000000000000000111010 $
#19
#20
b00000000000000000000000000001010 #
b00000000000000000000000000111011 $
b101 %
b00000000000000000000000000000001 &
#21
#22
b00000000000000000000000001000010 #
b00000000000000000000000000011110 $
b00000000000000000000000000000000 &
#23
#24
b00000000000000000000000000111111 #
b00000000000000000000000000000010 $
b010 %
b00000000000000000000000000000010 &
#25
#26
b00000000000000000000000001010111 #
b00000000000000000000000000100010 $
#27
#28
b00000000000000000000000000011001 #
b00000000000000000000000001100001 $
b00000000000000000000000000000001 &
#29
#30
b00000000000000000000000001000100 #
b00000000000000000000000001011010 $
b011 %
b00000000000000000000000001011110 &
#31
#32
b00000000000000000000000000011000 #
b00000000000000000000000001000011 $
b000 %
b00000000000000000000000001011011 &
#33
#34
b00000000000000000000000000101001 #
b00000000000000000000000001010001 $
b101 %
b00000000000000000000000000000001 &
#35
#36
b00000000000000000000000001000111 #
b00000000000000000000000001010101 $
b011 %
b00000000000000000000000001010111 &
#37
#38
b00000000000000000000000000000111 #
b00000000000000000000000001011100 $
b010 %
b00000000000000000000000000000100 &
