project/controlUnit/main_decoder.sv
module mainDecoder (
    //inputs:
    input logic [6:0]                   op_i,
    //outputs:
    output logic                        branch_o,
    output logic                        jump_o,
    output logic    [1:0]               result_src_o,
    output logic                        mem_write_o,
    output logic                        alu_src_o,
    output logic    [2:0]               imm_src_o,
    output logic                        reg_write_o,
    output logic    [1:0]               alu_op_o
);

always_comb begin

    case(op_i)

        //memory read instruction: lw
        7'b0000011 : begin
            reg_write_o = 1'b1;
            imm_src_o = 3'b000;
            alu_src_o = 1'b1;
            mem_write_o = 1'b0;
            result_src_o = 2'b01;
            branch_o = 1'b0;
            alu_op_o = 2'b00;
            jump_o = 1'b0;
        end

        //memory write instruction: sw
        7'b0100011 : begin
            reg_write_o = 1'b0;
            imm_src_o = 3'b001;
            alu_src_o = 1'b1;
            mem_write_o = 1'b1;
            result_src_o = 2'b00;//don't-care values 
            branch_o = 1'b0;
            alu_op_o = 2'b00;
            jump_o = 1'b0;
        end

        //register operation:
        7'b0110011 : begin
            reg_write_o = 1'b1;
            imm_src_o = 3'b000; //dont-care values
            alu_src_o = 1'b0;
            mem_write_o = 1'b0;
            result_src_o = 2'b00;
            branch_o = 1'b0;
            alu_op_o = 2'b10;
            jump_o = 1'b0;
        end

        //branch_o operation: beq
        7'b1100011 : begin
            reg_write_o = 1'b0;
            imm_src_o = 3'b010;
            alu_src_o = 1'b0;
            mem_write_o = 1'b0;
            result_src_o = 2'b00;//dont-care values
            branch_o = 1'b1;
            alu_op_o = 2'b01;
            jump_o = 1'b0;
        end

        //immediate operation:
        7'b0010011 : begin
            reg_write_o = 1'b1;
            imm_src_o = 3'b000;
            alu_src_o = 1'b1;
            mem_write_o = 1'b0;
            result_src_o = 2'b00;
            branch_o = 1'b0;
            alu_op_o = 2'b10;
            jump_o = 1'b0;
        end

        // Jump instruction JAL
        7'b1101111 : begin
            reg_write_o = 1'b1;
            imm_src_o = 3'b011;
            alu_src_o = 1'b0;//dont-care value
            mem_write_o = 1'b0;
            result_src_o = 2'b10;
            branch_o = 1'b0;
            alu_op_o = 2'b00;//dont-care value
            jump_o = 1'b1;
        end
        //Jump instrucation JALR
        7'b1100111 : begin
            reg_write_o = 1'b1;
            imm_src_o = 3'b000;
            alu_src_o = 1'b1;
            mem_write_o = 1'b0;
            result_src_o = 2'b10;
            branch_o = 1'b0;
            alu_op_o = 2'b10;
            jump_o = 1'b1;
        end
        //upper type : lui
        7'b0110111 : begin
            reg_write_o = 1'b1;
            imm_src_o = 3'b100;
            alu_src_o = 1'b1;
            mem_write_o = 1'b0;
            result_src_o = 2'b11;
            branch_o = 1'b0;
            alu_op_o = 2'b11;
            jump_o = 1'b0;
        end

        // reset all variables
        default : begin
            reg_write_o = 1'b1;
            imm_src_o = 3'b000; //dont-care values
            alu_src_o = 1'b0;
            mem_write_o = 1'b0;
            result_src_o = 2'b00;
            branch_o = 1'b0;
            alu_op_o = 2'b10;
            jump_o = 1'b0;
        end
    endcase
end;
endmodule

/* what do we want the default case to be? 
->perhaps we the default to reset the program counter (jump_o to first intruction)
->maybe we want it to do nothing (no-op) so do not increment program counter?

for not this has been set to register operation mode
*/

project/controlUnit/main_decoder.vcd
$version Generated by VerilatedVcd $end
$timescale 1ps $end

 $scope module TOP $end
  $var wire  2 + alu_op_o [1:0] $end
  $var wire  1 ( alu_src_o $end
  $var wire  1 $ branch_o $end
  $var wire  3 ) imm_src_o [2:0] $end
  $var wire  1 % jump_o $end
  $var wire  1 ' mem_write_o $end
  $var wire  7 # op_i [6:0] $end
  $var wire  1 * reg_write_o $end
  $var wire  2 & result_src_o [1:0] $end
  $scope module mainDecoder $end
   $var wire  2 + alu_op_o [1:0] $end
   $var wire  1 ( alu_src_o $end
   $var wire  1 $ branch_o $end
   $var wire  3 ) imm_src_o [2:0] $end
   $var wire  1 % jump_o $end
   $var wire  1 ' mem_write_o $end
   $var wire  7 # op_i [6:0] $end
   $var wire  1 * reg_write_o $end
   $var wire  2 & result_src_o [1:0] $end
  $upscope $end
 $upscope $end
$enddefinitions $end


#0
b0000000 #
0$
0%
b00 &
0'
0(
b000 )
0*
b00 +
#1
1*
b10 +
#2
b1101111 #
1%
b10 &
b011 )
b00 +
#3
#4
b1100111 #
1(
b000 )
b10 +
#5
#6
b0100011 #
0%
b00 &
1'
b001 )
0*
b00 +
#7
#8
b1100111 #
1%
b10 &
0'
b000 )
1*
b10 +
#9
#10
b1101111 #
0(
b011 )
b00 +
#11
#12
b0010011 #
0%
b00 &
1(
b000 )
b10 +
#13
#14
b1100011 #
1$
0(
b010 )
0*
b01 +
#15
#16
b1100111 #
0$
1%
b10 &
1(
b000 )
1*
b10 +
#17
#18
b1101111 #
0(
b011 )
b00 +
#19
#20
b0100011 #
0%
b00 &
1'
1(
b001 )
0*
#21
#22
b1101111 #
1%
b10 &
0'
0(
b011 )
1*
#23
#24
b1100111 #
1(
b000 )
b10 +
#25
#26
b0110111 #
0%
b11 &
b100 )
b11 +
#27
#28
b1101111 #
1%
b10 &
0(
b011 )
b00 +
#29
#30
b1100011 #
1$
0%
b00 &
b010 )
0*
b01 +
#31
#32
b0000011 #
0$
b01 &
1(
b000 )
1*
b00 +
#33
#34
b0100011 #
b00 &
1'
b001 )
0*
#35
#36
b1101111 #
1%
b10 &
0'
0(
b011 )
1*
#37
#38
#39
#40
b1100111 #
1(
b000 )
b10 +
#41
#42
#43
#44
b0110111 #
0%
b11 &
b100 )
b11 +
#45
#46
b0100011 #
b00 &
1'
b001 )
0*
b00 +
#47
#48
b1100011 #
1$
0'
0(
b010 )
b01 +
#49
#50
#51
#52
b1101111 #
0$
1%
b10 &
b011 )
1*
b00 +
#53
#54
b0110011 #
0%
b00 &
b000 )
b10 +
#55
#56
b1100111 #
1%
b10 &
1(
#57
#58
b0100011 #
0%
b00 &
1'
b001 )
0*
b00 +
#59
#60
b0110111 #
b11 &
0'
b100 )
1*
b11 +
#61
#62
b1100111 #
1%
b10 &
b000 )
b10 +
#63
#64
b1101111 #
0(
b011 )
b00 +
#65
#66
b1100011 #
1$
0%
b00 &
b010 )
0*
b01 +
#67
#68
b1100111 #
0$
1%
b10 &
1(
b000 )
1*
b10 +
#69
#70
b1101111 #
0(
b011 )
b00 +
#71
#72
b0110111 #
0%
b11 &
1(
b100 )
b11 +
#73
#74
b1100111 #
1%
b10 &
b000 )
b10 +
#75
#76
b0100011 #
0%
b00 &
1'
b001 )
0*
b00 +
#77
#78
b0110111 #
b11 &
0'
b100 )
1*
b11 +
#79
#80
b1101111 #
1%
b10 &
0(
b011 )
b00 +
#81
#82
b0010011 #
0%
b00 &
1(
b000 )
b10 +
#83
#84
b0000011 #
b01 &
b00 +
#85
#86
b1101111 #
1%
b10 &
0(
b011 )
#87
#88
#89
#90
#91
#92
b1100111 #
1(
b000 )
b10 +
#93
#94
b0010011 #
0%
b00 &
#95
#96
b1100011 #
1$
0(
b010 )
0*
b01 +
#97
#98
b1101111 #
0$
1%
b10 &
b011 )
1*
b00 +
#99
#100
b1100111 #
1(
b000 )
b10 +
#101
#102
b1101111 #
0(
b011 )
b00 +
#103
#104
b1100111 #
1(
b000 )
b10 +
#105
#106
b1101111 #
0(
b011 )
b00 +
#107
#108
b0010011 #
0%
b00 &
1(
b000 )
b10 +
#109
#110
b1100011 #
1$
0(
b010 )
0*
b01 +
#111
#112
b0000011 #
0$
b01 &
1(
b000 )
1*
b00 +
#113
#114
b1101111 #
1%
b10 &
0(
b011 )
#115
#116
b0000011 #
0%
b01 &
1(
b000 )
#117
#118
b0010011 #
b00 &
b10 +
#119
#120
#121
#122
b1100111 #
1%
b10 &
#123
#124
b0100011 #
0%
b00 &
1'
b001 )
0*
b00 +
#125
#126
b0110011 #
0'
0(
b000 )
1*
b10 +
#127
#128
#129
#130
b0010011 #
1(
#131
#132
#133
#134
b0110011 #
0(
#135
#136
b1100011 #
1$
b010 )
0*
b01 +
#137
#138
b0110111 #
0$
b11 &
1(
b100 )
1*
b11 +
#139
#140
b1100111 #
1%
b10 &
b000 )
b10 +
#141
#142
b0010011 #
0%
b00 &
#143
#144
b0110111 #
b11 &
b100 )
b11 +
#145
#146
b0110011 #
b00 &
0(
b000 )
b10 +
#147
#148
b0000011 #
b01 &
1(
b00 +
#149
#150
b1101111 #
1%
b10 &
0(
b011 )
#151
#152
b1100111 #
1(
b000 )
b10 +
#153
#154
b0010011 #
0%
b00 &
#155
#156
b1100011 #
1$
0(
b010 )
0*
b01 +
#157
#158
b1101111 #
0$
1%
b10 &
b011 )
1*
b00 +
#159
#160
b0100011 #
0%
b00 &
1'
1(
b001 )
0*
#161
#162
#163
#164
b1100011 #
1$
0'
0(
b010 )
b01 +
#165
#166
b0000011 #
0$
b01 &
1(
b000 )
1*
b00 +
#167
#168
#169
#170
#171
#172
b0010011 #
b00 &
b10 +
#173
#174
#175
#176
b0100011 #
1'
b001 )
0*
b00 +
#177
#178
b0110011 #
0'
0(
b000 )
1*
b10 +
#179
#180
b0110111 #
b11 &
1(
b100 )
b11 +
#181
#182
b0100011 #
b00 &
1'
b001 )
0*
b00 +
#183
#184
b0110011 #
0'
0(
b000 )
1*
b10 +
#185
#186
#187
#188
b0100011 #
1'
1(
b001 )
0*
b00 +
#189
#190
b0010011 #
0'
b000 )
1*
b10 +
#191
#192
b1100111 #
1%
b10 &
#193
#194
b1100011 #
1$
0%
b00 &
0(
b010 )
0*
b01 +
#195
#196
b1100111 #
0$
1%
b10 &
1(
b000 )
1*
b10 +
#197
#198
b0010011 #
0%
b00 &
#199
#200
b0000011 #
b01 &
b00 +
#201
#202
b0110011 #
b00 &
0(
b10 +
#203
#204
b1101111 #
1%
b10 &
b011 )
b00 +
#205
#206
b0000011 #
0%
b01 &
1(
b000 )
#207
#208
#209
#210
b0100011 #
b00 &
1'
b001 )
0*
#211
#212
b0110011 #
0'
0(
b000 )
1*
b10 +
#213
#214
b0000011 #
b01 &
1(
b00 +
#215
#216
b1101111 #
1%
b10 &
0(
b011 )
#217
#218
b1100011 #
1$
0%
b00 &
b010 )
0*
b01 +
#219
#220
b0110011 #
0$
b000 )
1*
b10 +
#221
#222
b0010011 #
1(
#223
#224
b0110011 #
0(
#225
#226
#227
#228
b1101111 #
1%
b10 &
b011 )
b00 +
#229
#230
b1100111 #
1(
b000 )
b10 +
#231
#232
b0000011 #
0%
b01 &
b00 +
#233
#234
b0110011 #
b00 &
0(
b10 +
#235
#236
b1100011 #
1$
b010 )
0*
b01 +
#237
#238
b1100111 #
0$
1%
b10 &
1(
b000 )
1*
b10 +
#239
#240
b0110011 #
0%
b00 &
0(
#241
#242
b0100011 #
1'
1(
b001 )
0*
b00 +
#243
#244
b0110111 #
b11 &
0'
b100 )
1*
b11 +
#245
#246
b1101111 #
1%
b10 &
0(
b011 )
b00 +
#247
#248
b0110011 #
0%
b00 &
b000 )
b10 +
#249
#250
b0010011 #
1(
#251
#252
b1101111 #
1%
b10 &
0(
b011 )
b00 +
#253
#254
b0010011 #
0%
b00 &
1(
b000 )
b10 +
#255
#256
b0110011 #
0(
#257
#258
b1100011 #
1$
b010 )
0*
b01 +
#259
#260
b0000011 #
0$
b01 &
1(
b000 )
1*
b00 +
#261
#262
b1101111 #
1%
b10 &
0(
b011 )
#263
#264
b0110111 #
0%
b11 &
1(
b100 )
b11 +
#265
#266
b0010011 #
b00 &
b000 )
b10 +
#267
#268
b1101111 #
1%
b10 &
0(
b011 )
b00 +
#269
#270
b0000011 #
0%
b01 &
1(
b000 )
#271
#272
b0100011 #
b00 &
1'
b001 )
0*
#273
#274
b1101111 #
1%
b10 &
0'
0(
b011 )
1*
#275
#276
b0110011 #
0%
b00 &
b000 )
b10 +
#277
#278
b0010011 #
1(
#279
#280
b1100111 #
1%
b10 &
#281
#282
b0000011 #
0%
b01 &
b00 +
#283
#284
b1100111 #
1%
b10 &
b10 +
#285
#286
b0100011 #
0%
b00 &
1'
b001 )
0*
b00 +
#287
#288
b1100011 #
1$
0'
0(
b010 )
b01 +
#289
#290
b1101111 #
0$
1%
b10 &
b011 )
1*
b00 +
#291
#292
b0010011 #
0%
b00 &
1(
b000 )
b10 +
#293
#294
b0110011 #
0(
#295
#296
b0110111 #
b11 &
1(
b100 )
b11 +
#297
#298
#299
#300
b0110011 #
b00 &
0(
b000 )
b10 +
#301
#302
b0100011 #
1'
1(
b001 )
0*
b00 +
#303
#304
b1100011 #
1$
0'
0(
b010 )
b01 +
#305
#306
b0000011 #
0$
b01 &
1(
b000 )
1*
b00 +
#307
#308
b1100011 #
1$
b00 &
0(
b010 )
0*
b01 +
#309
#310
b0110111 #
0$
b11 &
1(
b100 )
1*
b11 +
#311
#312
b1100011 #
1$
b00 &
0(
b010 )
0*
b01 +
#313
#314
b0010011 #
0$
1(
b000 )
1*
b10 +
#315
#316
#317
#318
#319
#320
b0000011 #
b01 &
b00 +
#321
#322
b1101111 #
1%
b10 &
0(
b011 )
#323
#324
b0010011 #
0%
b00 &
1(
b000 )
b10 +
#325
#326
#327
#328
b0110111 #
b11 &
b100 )
b11 +
#329
#330
b1101111 #
1%
b10 &
0(
b011 )
b00 +
#331
#332
#333
#334
b1100011 #
1$
0%
b00 &
b010 )
0*
b01 +
#335
#336
#337
#338
b1101111 #
0$
1%
b10 &
b011 )
1*
b00 +
#339
#340
b1100011 #
1$
0%
b00 &
b010 )
0*
b01 +
#341
#342
b0110011 #
0$
b000 )
1*
b10 +
#343
#344
b0000011 #
b01 &
1(
b00 +
#345
#346
b1101111 #
1%
b10 &
0(
b011 )
#347
#348
b1100111 #
1(
b000 )
b10 +
#349
#350
#351
#352
b1101111 #
0(
b011 )
b00 +
#353
#354
b0000011 #
0%
b01 &
1(
b000 )
#355
#356
b0110111 #
b11 &
b100 )
b11 +
#357
#358
#359
#360
b0110011 #
b00 &
0(
b000 )
b10 +
#361
#362
b1100111 #
1%
b10 &
1(
#363
#364
b0010011 #
0%
b00 &
#365
#366
b1100111 #
1%
b10 &
#367
#368
b0010011 #
0%
b00 &
#369
#370
b0110011 #
0(
#371
#372
b0100011 #
1'
1(
b001 )
0*
b00 +
#373
#374
b0000011 #
b01 &
0'
b000 )
1*
#375
#376
b1101111 #
1%
b10 &
0(
b011 )
#377
#378
b0100011 #
0%
b00 &
1'
1(
b001 )
0*
#379
#380
b0110011 #
0'
0(
b000 )
1*
b10 +
#381
#382
b0110111 #
b11 &
1(
b100 )
b11 +
#383
#384
b1100111 #
1%
b10 &
b000 )
b10 +
#385
#386
b0110011 #
0%
b00 &
0(
#387
#388
b1100011 #
1$
b010 )
0*
b01 +
#389
#390
b0110111 #
0$
b11 &
1(
b100 )
1*
b11 +
#391
#392
b0000011 #
b01 &
b000 )
b00 +
#393
#394
b0100011 #
b00 &
1'
b001 )
0*
#395
#396
b0010011 #
0'
b000 )
1*
b10 +
#397
#398
b1100111 #
1%
b10 &
