project/controlUnit/mainDecoder.sv
module mainDecoder (
    //inputs:
    input logic [6:0] op_i,
    //outputs:
    output logic branch_o,//branch_o and jump_o need to be or-ed together to determing the PCSrc signal.
    //schematic in lecture slide call for anding with zero which doesnt make sense???
    output logic jump_o,
    output logic [1:0] result_src_o,
    output logic mem_write_o,
    output logic alu_src_o,
    output logic [1:0] imm_src_o,
    output logic reg_write_o,
    output logic [1:0] alu_op_o
)

always_comb
    case(op_i)
        //memory read instruction: lw
        6'b0000011 : begin
            reg_write_o = 1'b1;
            imm_src_o = 2'b00;
            alu_src_o = 1'b1;
            mem_write_o = 1'b0;
            result_src_o = 2'b01;
            branch_o = 1'b0;
            alu_op_o = 2'b00;
            jump_o = 1'b0;
        end
        //memory write instruction: sw
        6'b0100011 : begin
            reg_write_o = 1'b0,
            imm_src_o = 1'b01;
            alu_src_o = 1'b1;
            mem_write_o = 1'b1;
            result_src_o = 2'b00;//don't-care values 
            branch_o = 1'b0;
            alu_op_o = 2'b00;
            jump_o = 1'b0;
        end
        //register operation:
        6'b0110011 : begin
            reg_write_o = 1'b1,
            imm_src_o = 1'b00; //dont-care values
            alu_src_o = 1'b0;
            mem_write_o = 1'b0;
            result_src_o = 2'b00;
            branch_o = 1'b0;
            alu_op_o = 2'b10;
            jump_o = 1'b0;
        end
        //branch_o opreation: beq
        6'b1100011 : begin
            reg_write_o = 1'b0,
            imm_src_o = 1'b10;
            alu_src_o = 1'b0;
            mem_write_o = 1'b0;
            result_src_o = 2'b00;//dont-care values
            branch_o = 1'b1;
            alu_op_o = 2'b01;
            jump_o = 1'b0;
        end
        //immediate operation:
        6'b0010011 : begin
            reg_write_o = 1'b1,
            imm_src_o = 1'b00;
            alu_src_o = 1'b1;
            mem_write_o = 1'b0;
            result_src_o = 2'b00;
            branch_o = 1'b0;
            alu_op_o = 2'b10;
            jump_o = 1'b0;
        end
        6'b1101111 : begin
            reg_write_o = 1'b1,
            imm_src_o = 1'b11;
            alu_src_o = 1'b0;//dont-care value
            mem_write_o = 1'b0;
            result_src_o = 2'b10;
            branch_o = 1'b0;
            alu_op_o = 2'b10;//dont-care value
            jump_o = 1'b1;
        end
        default : begin
            reg_write_o = 1'b1,
            imm_src_o = 1'b00; //dont-care values
            alu_src_o = 1'b0;
            mem_write_o = 1'b0;
            result_src_o = 2'b00;
            branch_o = 1'b0;
            alu_op_o = 2'b10;
            jump_o = 1'b0;
        end
    endcase
endmodule
/*what do we want the default case to be? 
->perhaps we the default to reset the program counter (jump_o to first intruction)
->maybe we want it to do nothing (no-op) so do not increment program counter?

for not this has been set to register operation mode
*/

project/controlUnit/main_decoder.vcd
$version Generated by VerilatedVcd $end
$timescale 1ps $end

 $scope module TOP $end
  $var wire  2 + alu_op_o [1:0] $end
  $var wire  1 ( alu_src_o $end
  $var wire  1 $ branch_o $end
  $var wire  2 ) imm_src_o [1:0] $end
  $var wire  1 % jump_o $end
  $var wire  1 ' mem_write_o $end
  $var wire  7 # op_i [6:0] $end
  $var wire  1 * reg_write_o $end
  $var wire  2 & result_src_o [1:0] $end
  $scope module mainDecoder $end
   $var wire  2 + alu_op_o [1:0] $end
   $var wire  1 ( alu_src_o $end
   $var wire  1 $ branch_o $end
   $var wire  2 ) imm_src_o [1:0] $end
   $var wire  1 % jump_o $end
   $var wire  1 ' mem_write_o $end
   $var wire  7 # op_i [6:0] $end
   $var wire  1 * reg_write_o $end
   $var wire  2 & result_src_o [1:0] $end
  $upscope $end
 $upscope $end
$enddefinitions $end


#0
b0000000 #
0$
0%
b00 &
0'
0(
b00 )
0*
b00 +
#1
1*
b10 +
#2
b1100011 #
1$
b10 )
0*
b01 +
#3
#4
b1101111 #
0$
1%
b10 &
b11 )
1*
b10 +
#5
#6
b0010011 #
0%
b00 &
1(
b00 )
#7
#8
#9
#10
b1100011 #
1$
0(
b10 )
0*
b01 +
#11
#12
#13
#14
b0110011 #
0$
b00 )
1*
b10 +
#15
#16
b1101111 #
1%
b10 &
b11 )
#17
#18
b0000011 #
0%
b01 &
1(
b00 )
b00 +
#19
#20
#21
#22
b1101111 #
1%
b10 &
0(
b11 )
b10 +
#23
#24
#25
#26
b0010011 #
0%
b00 &
1(
b00 )
#27
#28
b1101111 #
1%
b10 &
0(
b11 )
#29
#30
b1100011 #
1$
0%
b00 &
b10 )
0*
b01 +
#31
#32
b0100011 #
0$
1'
1(
b01 )
b00 +
#33
#34
#35
#36
b1100011 #
1$
0'
0(
b10 )
b01 +
