project/extend/extend_unit.sv
module extend_unit # (
    parameter DATA_WIDTH = 32
)(
    //input signals
    input  logic [INSTRUCT_WIDTH-1:7] instr_i, //instruction
    input  logic [2:0] imm_src_i,
    input logic [DATA_WIDTH-1:0] pc_i,
    
    //output
    output logic [DATA_WIDTH-1:0] imm_ext_o //output imm extended into 32 bits
);

always_comb
    case(immsrc)

        //type I
        3'b000: imm_ext_o = {{20{instr_i[31]}}, instr_i[31:20]};
        // type S
        3'b001: imm_ext_o = {{20{instr_i[31]}}, instr_i[31:25], instr_i[11:7]};
        //type B
        3'b010: imm_ext_o = {{20{instr_i[31]}}, instr_i[7], instr_i[30:25], instr_i[11:8], 1'b0}; 
        //type Jal
        3'b011: imm_ext_o = {{12{instr_i[31]}}, instr_i[19:12], instr_i[20], instr_i[30:21], 1'b0};
        
        //type U
        3'b100: imm_ext_o = {instr_i[31:12], 12{1'b0}};

        default: imm_ext_o = 32'b0;

    endcase

endmodule

project/extend/extend_unit.vcd
$version Generated by VerilatedVcd $end
$timescale 1ps $end

 $scope module TOP $end
  $var wire 32 % imm_ext_o [31:0] $end
  $var wire  3 $ imm_src_i [2:0] $end
  $var wire 25 # instr_i [31:7] $end
  $scope module extend_unit $end
   $var wire 32 & DATA_WIDTH [31:0] $end
   $var wire 32 % imm_ext_o [31:0] $end
   $var wire  3 $ imm_src_i [2:0] $end
   $var wire 25 # instr_i [31:7] $end
  $upscope $end
 $upscope $end
$enddefinitions $end


#0
b0000000000000000000000000 #
b000 $
b00000000000000000000000000000000 %
b00000000000000000000000000100000 &
#1
#2
b0011110110001100100111100 #
b100 $
b00111101100011001001000000000000 %
#3
#4
b0010010101010010101010001 #
b011 $
b00000000000000101010101001010100 %
#5
#6
b1011110001111111111011001 #
b001 $
b11111111111111111111101111011001 %
#7
#8
b1010000011010011100000000 #
b011 $
b11111111111100111000101000001100 %
#9
#10
b1101100101000101101010111 #
b100 $
b11011001010001011010000000000000 %
#11
#12
b1000111111000100111110001 #
b011 $
b11111111111101001111000011111100 %
#13
#14
b1001111000010010101000010 #
b001 $
b11111111111111111111100111100010 %
#15
#16
b0011001000110100101101000 #
b011 $
b00000000000001001011101100100010 %
#17
#18
b0001000010111001110110110 #
b010 $
b00000000000000000000000100010110 %
#19
#20
b1011111101010001101111110 #
b100 $
b10111111010100011011000000000000 %
#21
#22
b1010000001110010100011110 #
b000 $
b11111111111111111111101000000111 %
#23
#24
b1101010011101000001101101 #
b011 $
b11111111111110000011010101001110 %
#25
#26
b1100001101011001010110101 #
b001 $
b11111111111111111111110000110101 %
#27
#28
b0110011000011110000100001 #
b00000000000000000000011001100001 %
#29
#30
b0100100111011111011100110 #
b011 $
b00000000000011110111110010011100 %
#31
#32
b0010011110101010001011111 #
b000 $
b00000000000000000000001001111010 %
#33
#34
b0101010111110011010111001 #
b010 $
b00000000000000000000110101011000 %
#35
#36
b0001101000111010001111110 #
b100 $
b00011010001110100011000000000000 %
#37
#38
b1110011111001001101011100 #
b010 $
b11111111111111111111011001111100 %
