project/dataPath/alu/alu.sv
module alu #(
    parameter DATA_WIDTH = 32
)(
    input  logic [DATA_WIDTH-1:0] src1_i, src2_i,
    input  logic [3:0]            alu_control_i, // alu_control_i[3]   is funct7[5]
                                                 // alu_control_i[2:0] is funct3[2:0]
    output logic                  eq_o,
    output logic [DATA_WIDTH-1:0] alu_result_o
);

    always_comb begin 
        eq_o = (src1_i == src2_i);
        case (alu_control_i)
            // add
            4'b0000: alu_result_o = src1_i + src2_i;

            // shift left logical
            4'b0001: alu_result_o = src1_i << src2_i[4:0];

            // set less than
            4'b0010: alu_result_o = {{DATA_WIDTH-1{1'b0}}, (src1_i < src2_i)};

            // set less than unsigned
            4'b0011: alu_result_o = {{DATA_WIDTH-1{1'b0}}, ({1'b0, src1_i} < {1'b0, src2_i})};

            // xor
            4'b0100: alu_result_o = src1_i ^ src2_i;

            // shift right logical
            4'b0101: alu_result_o = src1_i >> src2_i[4:0];

            // or 
            4'b0110: alu_result_o = src1_i | src2_i;

            // and
            4'b0111: alu_result_o = src1_i & src2_i;

            // sub
            4'b1000: alu_result_o = src1_i - src2_i;

            // shift right arithmetic 
            4'b1101: alu_result_o = src1_i >>> src2_i[4:0];

            default: alu_result_o = {DATA_WIDTH{1'b0}};
        endcase 
    end

endmodule

project/dataPath/alu/alu.vcd
$version Generated by VerilatedVcd $end
$date Thu Nov 30 11:05:08 2023 $end
$timescale 1ps $end

 $scope module TOP $end
  $var wire  4 % alu_control_i [3:0] $end
  $var wire 32 ' alu_result_o [31:0] $end
  $var wire  1 & eq_o $end
  $var wire 32 # src1_i [31:0] $end
  $var wire 32 $ src2_i [31:0] $end
  $scope module alu $end
   $var wire 32 ( DATA_WIDTH [31:0] $end
   $var wire  4 % alu_control_i [3:0] $end
   $var wire 32 ' alu_result_o [31:0] $end
   $var wire  1 & eq_o $end
   $var wire 32 # src1_i [31:0] $end
   $var wire 32 $ src2_i [31:0] $end
  $upscope $end
 $upscope $end
$enddefinitions $end


#0
b00000000000000000000000000000000 #
b00000000000000000000000000000000 $
b0000 %
0&
b00000000000000000000000000000000 '
b00000000000000000000000000100000 (
#1
1&
#2
b00000000000000000000000000011110 #
b00000000000000000000000000001011 $
b0110 %
0&
b00000000000000000000000000011111 '
#3
#4
b00000000000000000000000001011010 #
b00000000000000000000000000000111 $
b0010 %
b00000000000000000000000000000000 '
#5
#6
b00000000000000000000000000111101 #
b00000000000000000000000000100111 $
#7
#8
b00000000000000000000000001001001 #
b00000000000000000000000000000101 $
b1000 %
b00000000000000000000000001000100 '
#9
#10
b00000000000000000000000000111000 #
b00000000000000000000000000101111 $
b1101 %
b00000000000000000000000000000000 '
#11
#12
b00000000000000000000000000100000 #
b0001 %
b00000000000100000000000000000000 '
#13
#14
b00000000000000000000000000011110 #
b00000000000000000000000000101100 $
b0000 %
b00000000000000000000000001001010 '
#15
#16
b00000000000000000000000000001011 #
b00000000000000000000000001100001 $
b0010 %
b00000000000000000000000000000001 '
#17
#18
b00000000000000000000000001011000 #
b00000000000000000000000000010110 $
b0100 %
b00000000000000000000000001001110 '
#19
#20
b00000000000000000000000000110101 #
b00000000000000000000000000111010 $
b0110 %
b00000000000000000000000000111111 '
#21
#22
b00000000000000000000000000100101 #
b00000000000000000000000001011000 $
b0111 %
b00000000000000000000000000000000 '
#23
#24
b00000000000000000000000000100011 #
b00000000000000000000000001001110 $
b00000000000000000000000000000010 '
#25
#26
b00000000000000000000000000111001 #
b00000000000000000000000000100111 $
b1000 %
b00000000000000000000000000010010 '
#27
#28
b00000000000000000000000001011010 #
b00000000000000000000000001000001 $
b0011 %
b00000000000000000000000000000000 '
#29
#30
b00000000000000000000000000110010 #
b00000000000000000000000000010101 $
b0000 %
b00000000000000000000000001000111 '
#31
#32
b00000000000000000000000000110001 #
b00000000000000000000000000110101 $
b0111 %
b00000000000000000000000000110001 '
#33
#34
b00000000000000000000000000101010 #
b00000000000000000000000000100011 $
b0100 %
b00000000000000000000000000001001 '
#35
#36
b00000000000000000000000000101100 #
b00000000000000000000000000101110 $
b0001 %
b00000000000010110000000000000000 '
#37
#38
b00000000000000000000000000010001 #
b00000000000000000000000001010110 $
b0100 %
b00000000000000000000000001000111 '
#39
#40
b00000000000000000000000000110101 #
b00000000000000000000000001011011 $
b00000000000000000000000001101110 '
#41
#42
b00000000000000000000000000100111 #
b00000000000000000000000000011100 $
b0010 %
b00000000000000000000000000000000 '
#43
#44
b00000000000000000000000001011001 #
b00000000000000000000000000010000 $
b0001 %
b00000000010110010000000000000000 '
#45
#46
b00000000000000000000000000101110 #
b00000000000000000000000001001001 $
b0010 %
b00000000000000000000000000000001 '
#47
#48
b00000000000000000000000001011110 #
b00000000000000000000000000001111 $
b0111 %
b00000000000000000000000000001110 '
#49
#50
b00000000000000000000000000000000 #
b00000000000000000000000001000001 $
b0000 %
b00000000000000000000000001000001 '
#51
#52
b00000000000000000000000000110100 #
b00000000000000000000000001000010 $
b0110 %
b00000000000000000000000001110110 '
#53
#54
b00000000000000000000000000000000 #
b00000000000000000000000000001001 $
b0011 %
b00000000000000000000000000000001 '
#55
#56
b00000000000000000000000001100000 #
b00000000000000000000000000110101 $
b0000 %
b00000000000000000000000010010101 '
#57
#58
b00000000000000000000000001011001 #
b00000000000000000000000000010110 $
b0110 %
b00000000000000000000000001011111 '
#59
#60
b00000000000000000000000000000101 #
b00000000000000000000000001001011 $
b1000 %
b11111111111111111111111110111010 '
#61
#62
b00000000000000000000000001001111 #
b00000000000000000000000001000011 $
b00000000000000000000000000001100 '
#63
#64
b00000000000000000000000001011110 #
b00000000000000000000000000001000 $
b0110 %
b00000000000000000000000001011110 '
#65
#66
b00000000000000000000000001010111 #
b00000000000000000000000000110110 $
b0000 %
b00000000000000000000000010001101 '
#67
#68
b00000000000000000000000000010011 #
b00000000000000000000000000000000 $
b0101 %
b00000000000000000000000000010011 '
#69
#70
b00000000000000000000000001000101 #
b00000000000000000000000000110100 $
b0011 %
b00000000000000000000000000000000 '
#71
#72
b00000000000000000000000001011011 #
b00000000000000000000000000000101 $
b1101 %
b00000000000000000000000000000010 '
#73
#74
b00000000000000000000000001000011 #
b00000000000000000000000000111001 $
b0000 %
b00000000000000000000000001111100 '
#75
#76
b00000000000000000000000000011111 #
b00000000000000000000000000000101 $
b0100 %
b00000000000000000000000000011010 '
#77
#78
b00000000000000000000000001011101 #
b00000000000000000000000001011110 $
b1000 %
b11111111111111111111111111111111 '
#79
#80
b00000000000000000000000000101001 #
b00000000000000000000000000110100 $
b0110 %
b00000000000000000000000000111101 '
#81
#82
b00000000000000000000000001010001 #
b00000000000000000000000001010011 $
b0011 %
b00000000000000000000000000000001 '
#83
#84
b00000000000000000000000000110010 #
b00000000000000000000000001001101 $
b0001 %
b00000000000001100100000000000000 '
#85
#86
b00000000000000000000000001010110 #
b00000000000000000000000001000000 $
b0111 %
b00000000000000000000000001000000 '
#87
#88
b00000000000000000000000000110000 #
b00000000000000000000000000100100 $
b1101 %
b00000000000000000000000000000011 '
#89
#90
b00000000000000000000000000011010 #
b00000000000000000000000000111001 $
b0010 %
b00000000000000000000000000000001 '
#91
#92
b00000000000000000000000001000101 #
b00000000000000000000000000110000 $
b1101 %
b00000000000000000000000000000000 '
#93
#94
b00000000000000000000000000011110 #
b00000000000000000000000000010000 $
b0110 %
b00000000000000000000000000011110 '
#95
#96
b00000000000000000000000000000001 #
b00000000000000000000000001100011 $
b0001 %
b00000000000000000000000000001000 '
#97
#98
b00000000000000000000000001001101 #
b00000000000000000000000001011100 $
b0111 %
b00000000000000000000000001001100 '
#99
#100
b00000000000000000000000001001011 #
b00000000000000000000000000100001 $
b1101 %
b00000000000000000000000000100101 '
#101
#102
b00000000000000000000000000000001 #
b00000000000000000000000000001111 $
b0011 %
b00000000000000000000000000000001 '
#103
#104
b00000000000000000000000000101110 #
b00000000000000000000000000010001 $
b0010 %
b00000000000000000000000000000000 '
#105
#106
b00000000000000000000000001100011 #
b00000000000000000000000000110111 $
b0111 %
b00000000000000000000000000100011 '
#107
#108
b00000000000000000000000000111010 #
b00000000000000000000000000111000 $
b0101 %
b00000000000000000000000000000000 '
#109
#110
b00000000000000000000000000010010 #
b00000000000000000000000001010010 $
b0010 %
b00000000000000000000000000000001 '
#111
#112
b00000000000000000000000001010010 #
b00000000000000000000000000000011 $
b00000000000000000000000000000000 '
#113
#114
b00000000000000000000000000000011 #
b00000000000000000000000000100001 $
b1000 %
b11111111111111111111111111100010 '
#115
#116
b00000000000000000000000000011101 #
b00000000000000000000000000100010 $
b1101 %
b00000000000000000000000000000111 '
#117
#118
b00000000000000000000000000001100 #
b00000000000000000000000000001011 $
b0001 %
b00000000000000000110000000000000 '
#119
#120
b00000000000000000000000001011001 #
b00000000000000000000000000100111 $
b0111 %
b00000000000000000000000000000001 '
#121
#122
b00000000000000000000000001000111 #
b00000000000000000000000000101000 $
b0100 %
b00000000000000000000000001101111 '
#123
#124
b00000000000000000000000000100100 #
b00000000000000000000000000100111 $
b0011 %
b00000000000000000000000000000001 '
#125
#126
b00000000000000000000000001001110 #
b00000000000000000000000000100110 $
b0000 %
b00000000000000000000000001110100 '
#127
#128
b00000000000000000000000000100101 #
b00000000000000000000000001100001 $
b0110 %
b00000000000000000000000001100101 '
#129
#130
b00000000000000000000000001010100 #
b00000000000000000000000001000011 $
b0000 %
b00000000000000000000000010010111 '
#131
#132
b00000000000000000000000000100100 #
b00000000000000000000000000000001 $
b0101 %
b00000000000000000000000000010010 '
#133
#134
b00000000000000000000000001011001 #
b00000000000000000000000000000100 $
b1101 %
b00000000000000000000000000000101 '
#135
#136
b00000000000000000000000000001001 #
b00000000000000000000000001010101 $
b0101 %
b00000000000000000000000000000000 '
#137
#138
b00000000000000000000000001010001 #
b00000000000000000000000001100001 $
b1101 %
b00000000000000000000000000101000 '
#139
#140
b00000000000000000000000000101100 #
b00000000000000000000000000100110 $
b1000 %
b00000000000000000000000000000110 '
#141
#142
b00000000000000000000000001011101 #
b00000000000000000000000000001001 $
b0000 %
b00000000000000000000000001100110 '
#143
#144
b00000000000000000000000000111001 #
b00000000000000000000000001100001 $
b0001 %
b00000000000000000000000001110010 '
#145
#146
b00000000000000000000000000101010 #
b00000000000000000000000001001100 $
b0000 %
b00000000000000000000000001110110 '
#147
#148
b00000000000000000000000001010011 #
b00000000000000000000000001000001 $
b1101 %
b00000000000000000000000000101001 '
#149
#150
b00000000000000000000000000011111 #
b00000000000000000000000000110010 $
b0110 %
b00000000000000000000000000111111 '
#151
#152
b00000000000000000000000000001110 #
b00000000000000000000000000100110 $
b0111 %
b00000000000000000000000000000110 '
#153
#154
b00000000000000000000000001100011 #
b00000000000000000000000000011011 $
b0011 %
b00000000000000000000000000000000 '
#155
#156
b00000000000000000000000000010010 #
b00000000000000000000000001011001 $
b1000 %
b11111111111111111111111110111001 '
#157
#158
b00000000000000000000000001001100 #
b00000000000000000000000000010110 $
b0101 %
b00000000000000000000000000000000 '
#159
#160
b00000000000000000000000001100001 #
b00000000000000000000000001000010 $
b00000000000000000000000000011000 '
#161
#162
b00000000000000000000000000111001 #
b00000000000000000000000000111100 $
b00000000000000000000000000000000 '
#163
#164
b00000000000000000000000001000101 $
b0100 %
b00000000000000000000000001111100 '
#165
#166
b00000000000000000000000000110001 #
b00000000000000000000000000001100 $
b0000 %
b00000000000000000000000000111101 '
#167
#168
b00000000000000000000000000011111 #
b00000000000000000000000000101111 $
b1000 %
b11111111111111111111111111110000 '
#169
#170
b00000000000000000000000000001010 #
b00000000000000000000000000011110 $
b11111111111111111111111111101100 '
#171
#172
b00000000000000000000000000111000 #
b00000000000000000000000000101100 $
b0110 %
b00000000000000000000000000111100 '
#173
#174
b00000000000000000000000000110111 #
b00000000000000000000000000111111 '
#175
#176
b00000000000000000000000000001010 #
b00000000000000000000000000001110 $
b0111 %
b00000000000000000000000000001010 '
#177
#178
b00000000000000000000000001100010 #
b00000000000000000000000001011010 $
b1101 %
b00000000000000000000000000000000 '
#179
#180
b00000000000000000000000000100011 #
b00000000000000000000000001010111 $
b0101 %
#181
#182
b00000000000000000000000000001010 #
b00000000000000000000000000101100 $
b0111 %
b00000000000000000000000000001000 '
#183
#184
b00000000000000000000000000101111 #
b00000000000000000000000000110110 $
b00000000000000000000000000100110 '
#185
#186
b00000000000000000000000001010010 #
b00000000000000000000000000110111 $
b0001 %
b00101001000000000000000000000000 '
#187
#188
b00000000000000000000000000101100 #
b00000000000000000000000000100110 $
b1000 %
b00000000000000000000000000000110 '
#189
#190
b00000000000000000000000001001000 #
b00000000000000000000000000110000 $
b00000000000000000000000000011000 '
#191
#192
b00000000000000000000000000000010 #
b00000000000000000000000000111000 $
b0011 %
b00000000000000000000000000000001 '
#193
#194
b00000000000000000000000000010011 #
b00000000000000000000000000111111 $
b1101 %
b00000000000000000000000000000000 '
#195
#196
b00000000000000000000000001000011 #
b00000000000000000000000001001001 $
b0011 %
b00000000000000000000000000000001 '
#197
#198
b00000000000000000000000000000100 #
b00000000000000000000000000010111 $
b0100 %
b00000000000000000000000000010011 '
#199
#200
b00000000000000000000000000001111 #
b00000000000000000000000000111010 $
b0011 %
b00000000000000000000000000000001 '
#201
#202
b00000000000000000000000001011100 #
b00000000000000000000000000010100 $
b0000 %
b00000000000000000000000001110000 '
#203
#204
b00000000000000000000000000011110 #
b00000000000000000000000001000100 $
b0110 %
b00000000000000000000000001011110 '
#205
#206
b00000000000000000000000001011001 #
b00000000000000000000000000000010 $
b0001 %
b00000000000000000000000101100100 '
#207
#208
b00000000000000000000000000111100 #
b00000000000000000000000001100010 $
b1101 %
b00000000000000000000000000001111 '
#209
#210
b00000000000000000000000000011110 #
b00000000000000000000000000010111 $
b00000000000000000000000000000000 '
#211
#212
b00000000000000000000000001001110 #
b00000000000000000000000000011001 $
b0101 %
#213
#214
b00000000000000000000000000010111 #
b00000000000000000000000001100000 $
b0000 %
b00000000000000000000000001110111 '
#215
#216
b00000000000000000000000000001100 #
b00000000000000000000000000111111 $
b0011 %
b00000000000000000000000000000001 '
#217
#218
b00000000000000000000000001000100 #
b00000000000000000000000000010011 $
b0110 %
b00000000000000000000000001010111 '
#219
#220
b00000000000000000000000000001110 #
b00000000000000000000000000100010 $
b00000000000000000000000000101110 '
#221
#222
b00000000000000000000000000101111 #
b00000000000000000000000000011011 $
b00000000000000000000000000111111 '
#223
#224
b00000000000000000000000000011101 #
b00000000000000000000000000001001 $
b00000000000000000000000000011101 '
#225
#226
b00000000000000000000000001000001 #
b00000000000000000000000000110010 $
b1000 %
b00000000000000000000000000001111 '
#227
#228
b00000000000000000000000000001000 #
b00000000000000000000000000001010 $
b0111 %
b00000000000000000000000000001000 '
#229
#230
b00000000000000000000000000100101 #
b00000000000000000000000001011100 $
b0010 %
b00000000000000000000000000000001 '
#231
#232
b00000000000000000000000000010010 #
b00000000000000000000000000010110 $
b0111 %
b00000000000000000000000000010010 '
#233
#234
b00000000000000000000000000000011 #
b00000000000000000000000000101110 $
b0110 %
b00000000000000000000000000101111 '
#235
#236
b00000000000000000000000000110111 #
b00000000000000000000000000001010 $
b1101 %
b00000000000000000000000000000000 '
#237
#238
b00000000000000000000000000011100 #
b00000000000000000000000000011110 $
b0001 %
#239
#240
b00000000000000000000000001001100 #
b00000000000000000000000000101100 $
b0101 %
#241
#242
b00000000000000000000000001010010 #
b0100 %
b00000000000000000000000001111110 '
#243
#244
b00000000000000000000000000001001 #
b00000000000000000000000001001001 $
b0101 %
b00000000000000000000000000000000 '
#245
#246
b00000000000000000000000000110111 #
b00000000000000000000000000100111 $
#247
#248
b00000000000000000000000000111000 #
b00000000000000000000000000101111 $
b0111 %
b00000000000000000000000000101000 '
#249
#250
b00000000000000000000000000000011 #
b00000000000000000000000000100101 $
b1101 %
b00000000000000000000000000000000 '
#251
#252
b00000000000000000000000001001101 #
b00000000000000000000000000110111 $
b0010 %
#253
#254
b00000000000000000000000000011000 #
b00000000000000000000000000001011 $
b0000 %
b00000000000000000000000000100011 '
#255
#256
b00000000000000000000000000010100 #
b00000000000000000000000001000010 $
b0010 %
b00000000000000000000000000000001 '
#257
#258
b00000000000000000000000000100000 #
b00000000000000000000000000101111 $
b0101 %
b00000000000000000000000000000000 '
#259
#260
b00000000000000000000000000111111 #
b00000000000000000000000000010111 $
b1101 %
#261
#262
b00000000000000000000000001010000 #
b00000000000000000000000000000110 $
b0011 %
#263
#264
b00000000000000000000000001001101 #
b00000000000000000000000001000011 $
b1101 %
b00000000000000000000000000001001 '
#265
#266
b00000000000000000000000000100010 #
b00000000000000000000000000010110 $
b1000 %
b00000000000000000000000000001100 '
#267
#268
b00000000000000000000000001011010 #
b00000000000000000000000001001110 $
b0111 %
b00000000000000000000000001001010 '
#269
#270
b00000000000000000000000000111011 #
b00000000000000000000000000100001 $
b0110 %
b00000000000000000000000000111011 '
#271
#272
b00000000000000000000000000010101 #
b00000000000000000000000000001010 $
b0100 %
b00000000000000000000000000011111 '
#273
#274
b00000000000000000000000000000101 #
b00000000000000000000000001010111 $
b0111 %
b00000000000000000000000000000101 '
#275
#276
b00000000000000000000000000100011 #
b00000000000000000000000000111011 $
b0011 %
b00000000000000000000000000000001 '
#277
#278
b00000000000000000000000001001111 #
b00000000000000000000000000101011 $
b0010 %
b00000000000000000000000000000000 '
#279
#280
b00000000000000000000000000110110 #
b00000000000000000000000000000110 $
b0110 %
b00000000000000000000000000110110 '
#281
#282
b00000000000000000000000000011010 #
b00000000000000000000000000100111 $
b0100 %
b00000000000000000000000000111101 '
#283
#284
b00000000000000000000000001011001 #
b00000000000000000000000000010000 $
b0011 %
b00000000000000000000000000000000 '
#285
#286
b00000000000000000000000000011110 #
b00000000000000000000000000110010 $
b0101 %
#287
#288
b00000000000000000000000000001010 #
b00000000000000000000000001011100 $
b0110 %
b00000000000000000000000001011110 '
#289
#290
b00000000000000000000000000100110 #
b00000000000000000000000000000100 $
b0001 %
b00000000000000000000001001100000 '
#291
#292
b00000000000000000000000000000110 #
b00000000000000000000000000011001 $
b0100 %
b00000000000000000000000000011111 '
#293
#294
b00000000000000000000000000011110 #
b00000000000000000000000000011110 $
b0011 %
1&
b00000000000000000000000000000000 '
#295
#296
b00000000000000000000000000010001 #
b00000000000000000000000000010001 $
b0010 %
#297
#298
b00000000000000000000000000010111 #
b00000000000000000000000001100000 $
b0110 %
0&
b00000000000000000000000001110111 '
#299
#300
b00000000000000000000000001001011 #
b00000000000000000000000000000011 $
b0100 %
b00000000000000000000000001001000 '
#301
#302
b00000000000000000000000000000011 #
b00000000000000000000000001010001 $
b0011 %
b00000000000000000000000000000001 '
#303
#304
b00000000000000000000000001011001 #
b00000000000000000000000000010110 $
b0001 %
b00010110010000000000000000000000 '
#305
#306
b00000000000000000000000000101010 #
b00000000000000000000000000110101 $
b0100 %
b00000000000000000000000000011111 '
#307
#308
b00000000000000000000000001000110 #
b00000000000000000000000000111111 $
b1000 %
b00000000000000000000000000000111 '
#309
#310
b00000000000000000000000000011100 #
b00000000000000000000000000110101 $
b0010 %
b00000000000000000000000000000001 '
#311
#312
b00000000000000000000000000010011 #
b00000000000000000000000000111100 $
b0111 %
b00000000000000000000000000010000 '
#313
#314
b00000000000000000000000000011001 #
b00000000000000000000000000101010 $
b1101 %
b00000000000000000000000000000000 '
#315
#316
b00000000000000000000000000010010 #
b00000000000000000000000000111100 $
b0110 %
b00000000000000000000000000111110 '
#317
#318
b00000000000000000000000001000111 #
b00000000000000000000000000100011 $
b0101 %
b00000000000000000000000000001000 '
#319
#320
b00000000000000000000000000010011 #
b00000000000000000000000000001010 $
b0000 %
b00000000000000000000000000011101 '
#321
#322
b00000000000000000000000000011001 #
b00000000000000000000000001000010 $
b0001 %
b00000000000000000000000001100100 '
#323
#324
b00000000000000000000000000010011 #
b00000000000000000000000000000111 $
b0011 %
b00000000000000000000000000000000 '
#325
#326
b00000000000000000000000000100000 #
b00000000000000000000000000000010 $
b0110 %
b00000000000000000000000000100010 '
#327
#328
b00000000000000000000000000110000 #
b00000000000000000000000001001000 $
b0000 %
b00000000000000000000000001111000 '
#329
#330
b00000000000000000000000000001001 #
b00000000000000000000000000110100 $
b0101 %
b00000000000000000000000000000000 '
#331
#332
b00000000000000000000000000010101 #
b00000000000000000000000000010111 $
#333
#334
b00000000000000000000000000001011 #
b00000000000000000000000000110001 $
b1000 %
b11111111111111111111111111011010 '
#335
#336
b00000000000000000000000000011110 #
b00000000000000000000000001000011 $
b0000 %
b00000000000000000000000001100001 '
#337
#338
b00000000000000000000000000010011 #
b00000000000000000000000001011010 $
b0101 %
b00000000000000000000000000000000 '
#339
#340
b00000000000000000000000000000100 #
b00000000000000000000000000111101 $
b0111 %
b00000000000000000000000000000100 '
#341
#342
b00000000000000000000000000101100 #
b00000000000000000000000001010111 $
b0101 %
b00000000000000000000000000000000 '
#343
#344
b00000000000000000000000001000001 #
b00000000000000000000000000111010 $
b0011 %
#345
#346
b00000000000000000000000000001000 #
b00000000000000000000000001011010 $
b0101 %
#347
#348
b00000000000000000000000000111001 #
b00000000000000000000000001011011 $
b1101 %
#349
#350
b00000000000000000000000001000101 #
b00000000000000000000000000000000 $
b0001 %
b00000000000000000000000001000101 '
#351
#352
b00000000000000000000000000100010 #
b00000000000000000000000001001001 $
b0100 %
b00000000000000000000000001101011 '
#353
#354
b00000000000000000000000000001100 #
b00000000000000000000000001010100 $
b0011 %
b00000000000000000000000000000001 '
#355
#356
b00000000000000000000000000100000 #
b00000000000000000000000001000011 $
#357
#358
b00000000000000000000000000001100 #
b00000000000000000000000001010110 $
b0101 %
b00000000000000000000000000000000 '
#359
#360
b00000000000000000000000001001111 #
b00000000000000000000000000101010 $
b0111 %
b00000000000000000000000000001010 '
#361
#362
b00000000000000000000000000001000 #
b00000000000000000000000001010110 $
b0100 %
b00000000000000000000000001011110 '
#363
#364
b00000000000000000000000000000100 #
b00000000000000000000000000000011 $
b0010 %
b00000000000000000000000000000000 '
#365
#366
b00000000000000000000000000000111 #
b00000000000000000000000000111111 $
b0100 %
b00000000000000000000000000111000 '
#367
#368
b00000000000000000000000000001100 #
b00000000000000000000000000010100 $
b0101 %
b00000000000000000000000000000000 '
#369
#370
b00000000000000000000000001011101 #
b00000000000000000000000000101001 $
b0111 %
b00000000000000000000000000001001 '
#371
#372
b00000000000000000000000001001010 #
b00000000000000000000000001001100 $
b0001 %
b00000000000001001010000000000000 '
#373
#374
b00000000000000000000000001001110 #
b00000000000000000000000001011000 $
b0111 %
b00000000000000000000000001001000 '
#375
#376
b00000000000000000000000001010100 #
b00000000000000000000000001001000 $
b0110 %
b00000000000000000000000001011100 '
#377
#378
b00000000000000000000000000111001 #
b00000000000000000000000001010100 $
b0100 %
b00000000000000000000000001101101 '
#379
#380
b00000000000000000000000000011000 #
b00000000000000000000000000001111 $
b0110 %
b00000000000000000000000000011111 '
#381
#382
b00000000000000000000000000000001 #
b00000000000000000000000000010111 $
b0010 %
b00000000000000000000000000000001 '
#383
#384
b00000000000000000000000001000001 #
b00000000000000000000000000011011 $
b0111 %
#385
#386
b00000000000000000000000000100111 #
b00000000000000000000000001010110 $
b0001 %
b00001001110000000000000000000000 '
#387
#388
b00000000000000000000000000111000 #
b00000000000000000000000000110010 $
b00000000111000000000000000000000 '
#389
#390
b00000000000000000000000000001011 #
b00000000000000000000000000101011 $
b0011 %
b00000000000000000000000000000001 '
#391
#392
b00000000000000000000000001000111 #
b00000000000000000000000000010001 $
b0001 %
b00000000100011100000000000000000 '
#393
#394
b00000000000000000000000000000100 #
b00000000000000000000000000110000 $
b00000000000001000000000000000000 '
#395
#396
b00000000000000000000000000010101 #
b00000000000000000000000000100000 $
b0011 %
b00000000000000000000000000000001 '
#397
#398
b00000000000000000000000000001010 #
b00000000000000000000000000101001 $
b1101 %
b00000000000000000000000000000000 '
