project/dataPath/alu/alu.sv
module alu #(
    parameter DATA_WIDTH = 32
)(
    input  logic [2:0]            alu_control_i,
    input  logic [DATA_WIDTH-1:0] src1_i, src2_i,
    output logic                  eq_o
    output logic [DATA_WIDTH-1:0] alu_result_o,
);

    always_comb begin 
        eq_o = (src1_i == src2_i);
        case (alu_control_i)
            // add
            3'b000:  alu_result_o = src1_i + src2_i;
            // subtract
            3'b001:  alu_result_o = src1_i - src2_i;
            // and
            3'b010:  alu_result_o = src1_i & src2_i;
            // or
            3'b011:  alu_result_o = src1_i | src2_i;
            // SLT
            3'b101:  alu_result_o = {{DATA_WIDTH-1{1'b0}}, (src1_i < src2_i)};
            default: alu_result_o = {DATA_WIDTH{1'b0}};
        endcase 
    end

endmodule

project/dataPath/alu/alu.vcd
$version Generated by VerilatedVcd $end
$date Sun Nov 26 16:13:30 2023 $end
$timescale 1ps $end

 $scope module TOP $end
  $var wire  3 % alu_control_i [2:0] $end
  $var wire 32 & alu_result_o [31:0] $end
  $var wire  1 ' eq_o $end
  $var wire 32 # src1_i [31:0] $end
  $var wire 32 $ src2_i [31:0] $end
  $scope module alu $end
   $var wire 32 ( DATA_WIDTH [31:0] $end
   $var wire  3 % alu_control_i [2:0] $end
   $var wire 32 & alu_result_o [31:0] $end
   $var wire  1 ' eq_o $end
   $var wire 32 # src1_i [31:0] $end
   $var wire 32 $ src2_i [31:0] $end
  $upscope $end
 $upscope $end
$enddefinitions $end


#0
b00000000000000000000000000000000 #
b00000000000000000000000000000000 $
b000 %
b00000000000000000000000000000000 &
0'
b00000000000000000000000000100000 (
#1
1'
#2
b00000000000000000000000001011000 #
b00000000000000000000000000100100 $
b010 %
0'
#3
#4
b00000000000000000000000000111011 #
b00000000000000000000000000111010 $
b001 %
b00000000000000000000000000000001 &
#5
#6
b00000000000000000000000001000100 #
b00000000000000000000000000000110 $
b010 %
b00000000000000000000000000000100 &
#7
#8
b00000000000000000000000000101100 #
b00000000000000000000000000111011 $
b000 %
b00000000000000000000000001100111 &
#9
#10
b00000000000000000000000000111000 #
b00000000000000000000000000000010 $
b010 %
b00000000000000000000000000000000 &
#11
#12
b00000000000000000000000000001010 #
b00000000000000000000000000011000 $
b000 %
b00000000000000000000000000100010 &
#13
#14
b00000000000000000000000000111001 #
b00000000000000000000000000100010 $
b00000000000000000000000001011011 &
#15
#16
b00000000000000000000000001001111 #
b00000000000000000000000000111110 $
b001 %
b00000000000000000000000000010001 &
#17
#18
b00000000000000000000000000000111 #
b00000000000000000000000000010111 $
b000 %
b00000000000000000000000000011110 &
#19
#20
b00000000000000000000000001010010 #
b00000000000000000000000000110100 $
b010 %
b00000000000000000000000000010000 &
#21
#22
b00000000000000000000000000000111 #
b00000000000000000000000000101000 $
b011 %
b00000000000000000000000000101111 &
#23
#24
b00000000000000000000000001000010 #
b00000000000000000000000000110011 $
b00000000000000000000000001110011 &
#25
#26
b00000000000000000000000000100000 #
b00000000000000000000000000010100 $
b000 %
b00000000000000000000000000110100 &
#27
#28
b00000000000000000000000000001011 #
b00000000000000000000000000010000 $
b101 %
b00000000000000000000000000000001 &
#29
#30
b00000000000000000000000000001110 #
b00000000000000000000000001001000 $
b011 %
b00000000000000000000000001001110 &
#31
#32
b00000000000000000000000000111000 #
b00000000000000000000000000100010 $
b00000000000000000000000000111010 &
#33
#34
b00000000000000000000000000011010 #
b00000000000000000000000000101011 $
b101 %
b00000000000000000000000000000001 &
#35
#36
b00000000000000000000000001011000 #
b00000000000000000000000001001010 $
b00000000000000000000000000000000 &
#37
#38
b00000000000000000000000000100111 #
b00000000000000000000000001010001 $
b010 %
b00000000000000000000000000000001 &
