project/pc/pc.sv
module pc # (
    parameter PC_WIDTH = 32
)(
    input                   clk, PCSrc, rst,
    input  [PC_WIDTH-1:0]   ImmExt,
    output [PC_WIDTH-1:0]   PC
);

    logic [PC_WIDTH-1:0] PCNext;

    initial begin 
        PCNext = 32'hBFC00000;
    end

    always_ff @ (posedge clk)
        if (rst)    PCNext <= 32'hBFC00000;
        else        PCNext <= PCSrc ? PC + ImmExt : PC + 32'd4;

    assign PC = PCNext;

endmodule

project/pc/pc.vcd
$version Generated by VerilatedVcd $end
$timescale 1ps $end

 $scope module TOP $end
  $var wire 32 & ImmExt [31:0] $end
  $var wire 32 ' PC [31:0] $end
  $var wire  1 $ PCSrc $end
  $var wire  1 # clk $end
  $var wire  1 % rst $end
  $scope module pc $end
   $var wire 32 & ImmExt [31:0] $end
   $var wire 32 ' PC [31:0] $end
   $var wire 32 ( PCNext [31:0] $end
   $var wire  1 $ PCSrc $end
   $var wire 32 ) PC_WIDTH [31:0] $end
   $var wire  1 # clk $end
   $var wire  1 % rst $end
  $upscope $end
 $upscope $end
$enddefinitions $end


#0
0#
0$
0%
b00000000000000000000000000000000 &
b10111111110000000000000000000000 '
b10111111110000000000000000000000 (
b00000000000000000000000000100000 )
#1
1#
b00000000000000000000000001000100 &
b10111111110000000000000000000100 '
b10111111110000000000000000000100 (
#2
0#
#3
1#
b00000000000000000000000000100100 &
b10111111110000000000000000001000 '
b10111111110000000000000000001000 (
#4
0#
#5
1#
b00000000000000000000000001000000 &
b10111111110000000000000000001100 '
b10111111110000000000000000001100 (
#6
0#
#7
1#
b00000000000000000000000000101000 &
b10111111110000000000000000010000 '
b10111111110000000000000000010000 (
#8
0#
#9
1#
1$
b00000000000000000000000000001100 &
b10111111110000000000000000010100 '
b10111111110000000000000000010100 (
#10
0#
#11
1#
0$
b00000000000000000000000001001100 &
b10111111110000000000000000100000 '
b10111111110000000000000000100000 (
#12
0#
#13
1#
b00000000000000000000000001011000 &
b10111111110000000000000000100100 '
b10111111110000000000000000100100 (
#14
0#
#15
1#
1$
b00000000000000000000000001010100 &
b10111111110000000000000000101000 '
b10111111110000000000000000101000 (
#16
0#
#17
1#
0$
b00000000000000000000000000010000 &
b10111111110000000000000001111100 '
b10111111110000000000000001111100 (
#18
0#
#19
1#
1$
b00000000000000000000000000011000 &
b10111111110000000000000010000000 '
b10111111110000000000000010000000 (
#20
0#
#21
1#
0$
b00000000000000000000000000001100 &
b10111111110000000000000010011000 '
b10111111110000000000000010011000 (
#22
0#
#23
1#
1$
b00000000000000000000000001001000 &
b10111111110000000000000010011100 '
b10111111110000000000000010011100 (
#24
0#
#25
1#
0$
b00000000000000000000000000111100 &
b10111111110000000000000011100100 '
b10111111110000000000000011100100 (
#26
0#
#27
1#
b00000000000000000000000001001000 &
b10111111110000000000000011101000 '
b10111111110000000000000011101000 (
#28
0#
#29
1#
1$
b00000000000000000000000000111100 &
b10111111110000000000000011101100 '
b10111111110000000000000011101100 (
#30
0#
#31
1#
b00000000000000000000000000100000 &
b10111111110000000000000100101000 '
b10111111110000000000000100101000 (
#32
0#
#33
1#
b00000000000000000000000000111000 &
b10111111110000000000000101001000 '
b10111111110000000000000101001000 (
#34
0#
#35
1#
0$
b00000000000000000000000001001100 &
b10111111110000000000000110000000 '
b10111111110000000000000110000000 (
#36
0#
#37
1#
b00000000000000000000000001001000 &
b10111111110000000000000110000100 '
b10111111110000000000000110000100 (
#38
0#
#39
1#
1$
b00000000000000000000000000110100 &
b10111111110000000000000110001000 '
b10111111110000000000000110001000 (
