project/pc/pc.sv
module pc # (
    parameter PC_WIDTH = 32
)(
    input                 clk_i, jump_taken_i, rst_i, jalr_instr_i,
    input  [PC_WIDTH-1:0] imm_ext_i, jta_jalr_i,
    output [PC_WIDTH-1:0] pc_o
);

    logic [PC_WIDTH-1:0] pc_next;

    initial begin 
        pc_next = 32'hBFC00000;
    end

    always_ff @ (posedge clk_i) begin
        if (rst_i)  pc_next <= 32'hBFC00000;
        else begin
            case (jalr_instr_i)
                1'b0: pc_next <= jump_taken_i ?  (pc_next + imm_ext_i) : (pc_next + 32'd4);
                1'b1: pc_next <= jta_jalr_i;
            endcase
            
        end
        
    end 

    assign pc_o = pc_next;

endmodule

project/pc/pc.vcd
$version Generated by VerilatedVcd $end
$timescale 1ps $end

 $scope module TOP $end
  $var wire  1 # clk_i $end
  $var wire 32 ' imm_ext_i [31:0] $end
  $var wire  1 & jalr_instr_i $end
  $var wire 32 ( jta_jalr_i [31:0] $end
  $var wire  1 $ jump_taken_i $end
  $var wire 32 ) pc_o [31:0] $end
  $var wire  1 % rst_i $end
  $scope module pc $end
   $var wire 32 + PC_WIDTH [31:0] $end
   $var wire  1 # clk_i $end
   $var wire 32 ' imm_ext_i [31:0] $end
   $var wire  1 & jalr_instr_i $end
   $var wire 32 ( jta_jalr_i [31:0] $end
   $var wire  1 $ jump_taken_i $end
   $var wire 32 * pc_next [31:0] $end
   $var wire 32 ) pc_o [31:0] $end
   $var wire  1 % rst_i $end
  $upscope $end
 $upscope $end
$enddefinitions $end


#0
1#
0$
0%
0&
b00000000000000000000000000000000 '
b00000000000000000000000000000000 (
b00000000000000000000000000000000 )
b00000000000000000000000000000000 *
b00000000000000000000000000100000 +
#1
0#
b10111111110000000000000000000000 )
b10111111110000000000000000000000 *
#2
1#
1%
b00000000000000000000000000011000 '
b10111111110000000000000000111000 (
#3
0#
#4
1#
0%
b00000000000000000000000000101000 '
b10111111110000000000000001011000 (
b10111111110000000000000000000100 )
b10111111110000000000000000000100 *
#5
0#
#6
1#
1$
b00000000000000000000000000010100 '
b10111111110000000000000000100000 (
b10111111110000000000000000011000 )
b10111111110000000000000000011000 *
#7
0#
#8
1#
1&
b00000000000000000000000001010100 '
b10111111110000000000000000111100 (
b10111111110000000000000000111100 )
b10111111110000000000000000111100 *
#9
0#
#10
1#
0$
0&
b00000000000000000000000001001000 '
b10111111110000000000000001011000 (
b10111111110000000000000001000000 )
b10111111110000000000000001000000 *
#11
0#
#12
1#
1$
b00000000000000000000000001011000 '
b10111111110000000000000000101000 (
b10111111110000000000000010011000 )
b10111111110000000000000010011000 *
#13
0#
#14
1#
0$
b00000000000000000000000001100000 '
b10111111110000000000000001001000 (
b10111111110000000000000010011100 )
b10111111110000000000000010011100 *
#15
0#
#16
1#
b00000000000000000000000001001000 '
b10111111110000000000000000011000 (
b10111111110000000000000010100000 )
b10111111110000000000000010100000 *
#17
0#
#18
1#
b00000000000000000000000000011100 '
b10111111110000000000000000010000 (
b10111111110000000000000010100100 )
b10111111110000000000000010100100 *
#19
0#
#20
1#
b00000000000000000000000000110100 '
b10111111110000000000000000100000 (
b10111111110000000000000010101000 )
b10111111110000000000000010101000 *
#21
0#
#22
1#
1%
b00000000000000000000000000111000 '
b10111111110000000000000000010100 (
b10111111110000000000000000000000 )
b10111111110000000000000000000000 *
#23
0#
#24
1#
1$
0%
b00000000000000000000000000100100 '
b10111111110000000000000000001100 (
b10111111110000000000000000100100 )
b10111111110000000000000000100100 *
#25
0#
#26
1#
b00000000000000000000000000001100 '
b10111111110000000000000000000000 (
b10111111110000000000000000110000 )
b10111111110000000000000000110000 *
#27
0#
#28
1#
b00000000000000000000000000010000 '
b10111111110000000000000000010100 (
b10111111110000000000000001000000 )
b10111111110000000000000001000000 *
#29
0#
#30
1#
0$
b00000000000000000000000000101000 '
b10111111110000000000000000011100 (
b10111111110000000000000001000100 )
b10111111110000000000000001000100 *
#31
0#
#32
1#
b00000000000000000000000001100000 '
b10111111110000000000000000001000 (
b10111111110000000000000001001000 )
b10111111110000000000000001001000 *
#33
0#
#34
1#
1$
b00000000000000000000000000010000 '
b10111111110000000000000001000000 (
b10111111110000000000000001011000 )
b10111111110000000000000001011000 *
#35
0#
#36
1#
0$
b00000000000000000000000000111100 '
b10111111110000000000000000010100 (
b10111111110000000000000001011100 )
b10111111110000000000000001011100 *
#37
0#
#38
1#
1$
1&
b00000000000000000000000000010100 '
b10111111110000000000000001100000 (
b10111111110000000000000001100000 )
b10111111110000000000000001100000 *
