project/instructMem/instruction_memory.sv
module instruction_memory #(
    parameter   BYTE_SIZE = 8,
                DATA_WIDTH = 32,
                FIRST_INSTR_ADDR = 32'hBFC00000,
                LAST_INSTR_ADDR  = 32'hBFC00FFF
)(
    input  logic [DATA_WIDTH-1:0] addr_i,
    output logic [DATA_WIDTH-1:0] instr_o
);

logic [BYTE_SIZE-1:0] rom [LAST_INSTR_ADDR:FIRST_INSTR_ADDR];

initial begin

    $display("Loading rom.");
    $readmemh("instructions.hex", rom);
    $display("Program written to ROM successfully");

end;

logic [DATA_WIDTH-1:0] addr = addr_i & 32'hFFFFFFFC;

assign instr_o = {rom[addr+32'd3], rom[addr+32'd2], rom[addr+32'd1], rom[addr+32'd0]};

endmodule

project/instructMem/instruction_memory.vcd
$version Generated by VerilatedVcd $end
$date Fri Dec 15 15:59:12 2023 $end
$timescale 1ps $end

 $scope module TOP $end
  $var wire 32 # addr_i [31:0] $end
  $var wire 32 $ instr_o [31:0] $end
  $scope module instruction_memory $end
   $var wire 32 & BYTE_SIZE [31:0] $end
   $var wire 32 ' DATA_WIDTH [31:0] $end
   $var wire 32 ( FIRST_INSTR_ADDR [31:0] $end
   $var wire 32 ) LAST_INSTR_ADDR [31:0] $end
   $var wire 32 % addr [31:0] $end
   $var wire 32 # addr_i [31:0] $end
   $var wire 32 $ instr_o [31:0] $end
  $upscope $end
 $upscope $end
$enddefinitions $end


#0
b00000000000000000000000000000000 #
b00000000000000000000000000000000 $
b00000000000000000000000000000000 %
b00000000000000000000000000001000 &
b00000000000000000000000000100000 '
b10111111110000000000000000000000 (
b10111111110000000000111111111111 )
#1
b00010011000000111111000000001111 $
#2
b10111111110000000000000000000111 #
b00010011000001010000000000000000 $
b10111111110000000000000000000100 %
#3
#4
b10111111110000000000000000011000 #
b11100011000110000000001111111110 $
b10111111110000000000000000011000 %
#5
#6
b10111111110000000000000000011001 #
#7
#8
b10111111110000000000000000010011 #
b10010011100001010001010100000000 $
b10111111110000000000000000010000 %
#9
#10
b10111111110000000000000000000001 #
b00010011000000111111000000001111 $
b10111111110000000000000000000000 %
#11
#12
b10111111110000000000000000010001 #
b10010011100001010001010100000000 $
b10111111110000000000000000010000 %
#13
#14
b10111111110000000000000000001101 #
b00010011100001010000010100000000 $
b10111111110000000000000000001100 %
#15
#16
b10111111110000000000000000001100 #
#17
#18
b10111111110000000000000000011001 #
b11100011000110000000001111111110 $
b10111111110000000000000000011000 %
#19
#20
b10111111110000000000000000011011 #
#21
#22
b10111111110000000000000000011001 #
#23
#24
b10111111110000000000000000010111 #
b11100011100111000110010111111110 $
b10111111110000000000000000010100 %
#25
#26
b10111111110000000000000000010010 #
b10010011100001010001010100000000 $
b10111111110000000000000000010000 %
#27
#28
b10111111110000000000000000001111 #
b00010011100001010000010100000000 $
b10111111110000000000000000001100 %
#29
#30
b10111111110000000000000000001101 #
#31
#32
b10111111110000000000000000011010 #
b11100011000110000000001111111110 $
b10111111110000000000000000011000 %
#33
#34
b10111111110000000000000000000010 #
b00010011000000111111000000001111 $
b10111111110000000000000000000000 %
#35
#36
b10111111110000000000000000011000 #
b11100011000110000000001111111110 $
b10111111110000000000000000011000 %
#37
#38
b10111111110000000000000000011001 #
