PC/pc.sv
module pc # (
    parameter   PC_WIDTH = 32
)(
    input                   clk,
    input                   rst,
    input                   PCsrc,
    input   [PC_WIDTH-1:0]  ImmOp,
    output  [PC_WIDTH-1:0]  PC
);

    logic   [PC_WIDTH-1:0]  program_counter;

    initial begin 
        program_counter = {PC_WIDTH{1'b0}};
    end

    always_ff @ (posedge clk) begin

        if (rst)    program_counter <= {PC_WIDTH{1'b0}};
        else        program_counter <= PCsrc ? program_counter + ImmOp : program_counter + 32'd4;

    end

    assign PC = program_counter;

endmodule

PC/pc.vcd
$version Generated by VerilatedVcd $end
$timescale 1ps $end

 $scope module TOP $end
  $var wire 32 & ImmOp [31:0] $end
  $var wire 32 ' PC [31:0] $end
  $var wire  1 % PCsrc $end
  $var wire  1 # clk $end
  $var wire  1 $ rst $end
  $scope module pc $end
   $var wire 32 & ImmOp [31:0] $end
   $var wire 32 ' PC [31:0] $end
   $var wire 32 ) PC_WIDTH [31:0] $end
   $var wire  1 % PCsrc $end
   $var wire  1 # clk $end
   $var wire 32 ( program_counter [31:0] $end
   $var wire  1 $ rst $end
  $upscope $end
 $upscope $end
$enddefinitions $end


#0
0#
0$
0%
b00000000000000000000000000000000 &
b00000000000000000000000000000000 '
b00000000000000000000000000000000 (
b00000000000000000000000000100000 )
#1
1#
b00000000000000000000000000110000 &
b00000000000000000000000000000100 '
b00000000000000000000000000000100 (
#2
0#
#3
1#
b00000000000000000000000000001000 &
b00000000000000000000000000001000 '
b00000000000000000000000000001000 (
#4
0#
#5
1#
1%
b00000000000000000000000001100000 &
b00000000000000000000000000001100 '
b00000000000000000000000000001100 (
#6
0#
#7
1#
0%
b00000000000000000000000000110100 &
b00000000000000000000000001101100 '
b00000000000000000000000001101100 (
#8
0#
#9
1#
b00000000000000000000000000100000 &
b00000000000000000000000001110000 '
b00000000000000000000000001110000 (
#10
0#
#11
1#
1%
b00000000000000000000000001000100 &
b00000000000000000000000001110100 '
b00000000000000000000000001110100 (
#12
0#
#13
1#
0%
b00000000000000000000000001011000 &
b00000000000000000000000010111000 '
b00000000000000000000000010111000 (
#14
0#
#15
1#
b00000000000000000000000001100000 &
b00000000000000000000000010111100 '
b00000000000000000000000010111100 (
#16
0#
#17
1#
b00000000000000000000000001000000 &
b00000000000000000000000011000000 '
b00000000000000000000000011000000 (
#18
0#
#19
1#
b00000000000000000000000000110000 &
b00000000000000000000000011000100 '
b00000000000000000000000011000100 (
#20
0#
#21
1#
1%
b00000000000000000000000001010000 &
b00000000000000000000000011001000 '
b00000000000000000000000011001000 (
#22
0#
#23
1#
0%
b00000000000000000000000000100100 &
b00000000000000000000000100011000 '
b00000000000000000000000100011000 (
#24
0#
#25
1#
1%
b00000000000000000000000000101000 &
b00000000000000000000000100011100 '
b00000000000000000000000100011100 (
#26
0#
#27
1#
b00000000000000000000000001011100 &
b00000000000000000000000101000100 '
b00000000000000000000000101000100 (
#28
0#
#29
1#
b00000000000000000000000000110100 &
b00000000000000000000000110100000 '
b00000000000000000000000110100000 (
#30
0#
#31
1#
0%
b00000000000000000000000001001000 &
b00000000000000000000000111010100 '
b00000000000000000000000111010100 (
#32
0#
#33
1#
b00000000000000000000000000010000 &
b00000000000000000000000111011000 '
b00000000000000000000000111011000 (
#34
0#
#35
1#
b00000000000000000000000000100100 &
b00000000000000000000000111011100 '
b00000000000000000000000111011100 (
#36
0#
#37
1#
1%
b00000000000000000000000001000000 &
b00000000000000000000000111100000 '
b00000000000000000000000111100000 (
#38
0#
#39
1#
b00000000000000000000000000010000 &
b00000000000000000000001000100000 '
b00000000000000000000001000100000 (
