project/registerFile/register_file.sv
module register_file #(
    parameter ADDRESS_WIDTH = 5,
              DATA_WIDTH    = 32
)(
    input  logic                     addr3_we_i, clk_i,
    input  logic [ADDRESS_WIDTH-1:0] addr1_i, addr2_i, addr3_i,
    input  logic [DATA_WIDTH-1:0]    addr3_wd_i,
    output logic [DATA_WIDTH-1:0]    rd1_o, rd2_o
);

    logic [DATA_WIDTH-1:0] rf[2**ADDRESS_WIDTH-1:0];

    initial begin
        for (int i = 0; i < 32; i++)
            rf[i] = {DATA_WIDTH{1'b0}};
    end

    assign rd1_o = rf[addr1_i];
    assign rd2_o = rf[addr2_i];
    
    always_ff @(negedge clk_i) begin
        if (addr3_we_i && addr3_i != 0) begin
            rf[addr3_i] <= addr3_wd_i;
        end
    end

endmodule

project/dataPath/registerFile/register_file.vcd
$version Generated by VerilatedVcd $end
$date Sat Dec  2 14:49:11 2023 $end
$timescale 1ps $end

 $scope module TOP $end
  $var wire  5 F addr1_i [4:0] $end
  $var wire  5 G addr2_i [4:0] $end
  $var wire  5 H addr3_i [4:0] $end
  $var wire 32 I addr3_wd_i [31:0] $end
  $var wire  1 D addr3_we_i $end
  $var wire  1 E clk_i $end
  $var wire 32 J rd1_o [31:0] $end
  $var wire 32 K rd2_o [31:0] $end
  $scope module register_file $end
   $var wire 32 L ADDRESS_WIDTH [31:0] $end
   $var wire 32 M DATA_WIDTH [31:0] $end
   $var wire  5 F addr1_i [4:0] $end
   $var wire  5 G addr2_i [4:0] $end
   $var wire  5 H addr3_i [4:0] $end
   $var wire 32 I addr3_wd_i [31:0] $end
   $var wire  1 D addr3_we_i $end
   $var wire  1 E clk_i $end
   $var wire 32 J rd1_o [31:0] $end
   $var wire 32 K rd2_o [31:0] $end
   $var wire 32 $ rf[0] [31:0] $end
   $var wire 32 . rf[10] [31:0] $end
   $var wire 32 / rf[11] [31:0] $end
   $var wire 32 0 rf[12] [31:0] $end
   $var wire 32 1 rf[13] [31:0] $end
   $var wire 32 2 rf[14] [31:0] $end
   $var wire 32 3 rf[15] [31:0] $end
   $var wire 32 4 rf[16] [31:0] $end
   $var wire 32 5 rf[17] [31:0] $end
   $var wire 32 6 rf[18] [31:0] $end
   $var wire 32 7 rf[19] [31:0] $end
   $var wire 32 % rf[1] [31:0] $end
   $var wire 32 8 rf[20] [31:0] $end
   $var wire 32 9 rf[21] [31:0] $end
   $var wire 32 : rf[22] [31:0] $end
   $var wire 32 ; rf[23] [31:0] $end
   $var wire 32 < rf[24] [31:0] $end
   $var wire 32 = rf[25] [31:0] $end
   $var wire 32 > rf[26] [31:0] $end
   $var wire 32 ? rf[27] [31:0] $end
   $var wire 32 @ rf[28] [31:0] $end
   $var wire 32 A rf[29] [31:0] $end
   $var wire 32 & rf[2] [31:0] $end
   $var wire 32 B rf[30] [31:0] $end
   $var wire 32 C rf[31] [31:0] $end
   $var wire 32 ' rf[3] [31:0] $end
   $var wire 32 ( rf[4] [31:0] $end
   $var wire 32 ) rf[5] [31:0] $end
   $var wire 32 * rf[6] [31:0] $end
   $var wire 32 + rf[7] [31:0] $end
   $var wire 32 , rf[8] [31:0] $end
   $var wire 32 - rf[9] [31:0] $end
   $scope module unnamedblk1 $end
    $var wire 32 # i [31:0] $end
   $upscope $end
  $upscope $end
 $upscope $end
$enddefinitions $end


#0
b00000000000000000000000000000000 #
b00000000000000000000000000000000 $
b00000000000000000000000000000000 %
b00000000000000000000000000000000 &
b00000000000000000000000000000000 '
b00000000000000000000000000000000 (
b00000000000000000000000000000000 )
b00000000000000000000000000000000 *
b00000000000000000000000000000000 +
b00000000000000000000000000000000 ,
b00000000000000000000000000000000 -
b00000000000000000000000000000000 .
b00000000000000000000000000000000 /
b00000000000000000000000000000000 0
b00000000000000000000000000000000 1
b00000000000000000000000000000000 2
b00000000000000000000000000000000 3
b00000000000000000000000000000000 4
b00000000000000000000000000000000 5
b00000000000000000000000000000000 6
b00000000000000000000000000000000 7
b00000000000000000000000000000000 8
b00000000000000000000000000000000 9
b00000000000000000000000000000000 :
b00000000000000000000000000000000 ;
b00000000000000000000000000000000 <
b00000000000000000000000000000000 =
b00000000000000000000000000000000 >
b00000000000000000000000000000000 ?
b00000000000000000000000000000000 @
b00000000000000000000000000000000 A
b00000000000000000000000000000000 B
b00000000000000000000000000000000 C
0D
1E
b00000 F
b00000 G
b00000 H
b00000000000000000000000000000000 I
b00000000000000000000000000000000 J
b00000000000000000000000000000000 K
b00000000000000000000000000000101 L
b00000000000000000000000000100000 M
#1
b00000000000000000000000000100000 #
0E
#2
1D
1E
b00111 F
b00011 G
b10011 H
b00000000000000000000000100110001 I
#3
b00000000000000000000000100110001 7
0E
#4
0D
1E
b11001 F
b11101 G
b01001 H
b00000000000000000000000000111100 I
#5
0E
#6
1D
1E
b00000 F
b00110 G
b01000 H
b00000000000000000000000010110011 I
#7
b00000000000000000000000010110011 ,
0E
#8
0D
1E
b10111 F
b00111 G
b00001 H
b00000000000000000000001110110000 I
#9
0E
#10
1D
1E
b00001 F
b01000 G
b10101 H
b00000000000000000000001110011000 I
b00000000000000000000000010110011 K
#11
b00000000000000000000001110011000 9
0E
#12
1E
b10111 F
b00101 G
b11010 H
b00000000000000000000001110010110 I
b00000000000000000000000000000000 K
#13
b00000000000000000000001110010110 >
0E
#14
0D
1E
b00110 G
b00010 H
b00000000000000000000001000001001 I
#15
0E
#16
1E
b01011 F
b00100 G
b01111 H
b00000000000000000000000010010100 I
#17
0E
#18
1D
1E
b11011 F
b10100 G
b11011 H
b00000000000000000000001111000011 I
#19
b00000000000000000000001111000011 ?
0E
b00000000000000000000001111000011 J
#20
0D
1E
b00110 F
b11010 G
b01010 H
b00000000000000000000000011110100 I
b00000000000000000000000000000000 J
b00000000000000000000001110010110 K
#21
0E
#22
1D
1E
b00010 F
b01001 G
b11101 H
b00000000000000000000000011000100 I
b00000000000000000000000000000000 K
#23
b00000000000000000000000011000100 A
0E
#24
1E
b11101 F
b01111 G
b00001 H
b00000000000000000000000111000110 I
b00000000000000000000000011000100 J
#25
b00000000000000000000000111000110 %
0E
#26
0D
1E
b00000 F
b01110 G
b10100 H
b00000000000000000000000100010001 I
b00000000000000000000000000000000 J
#27
0E
#28
1D
1E
b00110 F
b01101 G
b11101 H
b00000000000000000000001001100001 I
#29
b00000000000000000000001001100001 A
0E
#30
0D
1E
b10001 F
b10000 G
b10101 H
b00000000000000000000000100001011 I
#31
0E
#32
1E
b11000 F
b10011 G
b01101 H
b00000000000000000000001101010011 I
b00000000000000000000000100110001 K
#33
0E
#34
1D
1E
b00010 F
b00101 G
b00100 H
b00000000000000000000001011001100 I
b00000000000000000000000000000000 K
#35
b00000000000000000000001011001100 (
0E
#36
1E
b00000 F
b11100 G
b01011 H
b00000000000000000000001001000100 I
#37
b00000000000000000000001001000100 /
0E
#38
0D
1E
b11001 F
b00001 G
b00010 H
b00000000000000000000001001000011 I
b00000000000000000000000111000110 K
